{"8": {"MMR": 0, "_id": 8, "name": "Alchemists Lab", "prestige": 400, "prestige_lvl": 400}, "85": {"MMR": 0, "_id": 85, "name": "ONNI", "prestige": 425, "prestige_lvl": 425}, "108": {"MMR": 558, "_id": 108, "name": "The Hive", "prestige": 11514, "prestige_lvl": 1150}, "161": {"MMR": 0, "_id": 161, "name": "Game of Thrones", "prestige": 400, "prestige_lvl": 400}, "200": {"MMR": 804, "_id": 200, "name": "New World Order", "prestige": 16022, "prestige_lvl": 1550}, "238": {"MMR": 1000, "_id": 238, "name": "~Alchemists of Fire~", "prestige": 29161, "prestige_lvl": 1875}, "355": {"MMR": 352, "_id": 355, "name": "Kingdom of Jerusalem", "prestige": 7261, "prestige_lvl": 925}, "821": {"MMR": 0, "_id": 821, "name": "\u0395\u039b\u039b\u0391\u03a3", "prestige": 725, "prestige_lvl": 725}, "1204": {"MMR": 0, "_id": 1204, "name": "City", "prestige": 375, "prestige_lvl": 375}, "1367": {"MMR": 379, "_id": 1367, "name": "Alchemists Academy", "prestige": 8055, "prestige_lvl": 1225}, "1528": {"MMR": 650, "_id": 1528, "name": "Independent Warriors", "prestige": 14239, "prestige_lvl": 1550}, "2332": {"MMR": 438, "_id": 2332, "name": "Wolves of the Sea", "prestige": 8809, "prestige_lvl": 925}, "2511": {"MMR": 0, "_id": 2511, "name": "amithrc", "prestige": 375, "prestige_lvl": 375}, "3263": {"MMR": 0, "_id": 3263, "name": "chobo", "prestige": 400, "prestige_lvl": 400}, "3432": {"MMR": 442, "_id": 3432, "name": "The Trade Union", "prestige": 9071, "prestige_lvl": 1075}, "3443": {"MMR": 514, "_id": 3443, "name": "Grt British Warriors", "prestige": 10502, "prestige_lvl": 1250}, "3747": {"MMR": 547, "_id": 3747, "name": "Renegades", "prestige": 21338, "prestige_lvl": 1675}, "3925": {"MMR": 50, "_id": 3925, "name": "Bravehearts", "prestige": 1650, "prestige_lvl": 750}, "4115": {"MMR": 541, "_id": 4115, "name": "\u041c\u0410\u041a\u0415\u0414\u041e\u041d\u0418\u0408\u0410", "prestige": 10688, "prestige_lvl": 950}, "4168": {"MMR": 275, "_id": 4168, "name": "Croatans", "prestige": 5675, "prestige_lvl": 725}, "4199": {"MMR": 0, "_id": 4199, "name": "Knights Of Tyrranny", "prestige": 450, "prestige_lvl": 450}, "4471": {"MMR": 0, "_id": 4471, "name": "Winterfell", "prestige": 825, "prestige_lvl": 825}, "4528": {"MMR": 0, "_id": 4528, "name": "Flag united", "prestige": 325, "prestige_lvl": 325}, "4862": {"MMR": 446, "_id": 4862, "name": "Thor's Hammers", "prestige": 8778, "prestige_lvl": 750}, "4964": {"MMR": 0, "_id": 4964, "name": "The Forge", "prestige": 325, "prestige_lvl": 325}, "5062": {"MMR": 0, "_id": 5062, "name": "Trojan Fellowship", "prestige": 475, "prestige_lvl": 475}, "5304": {"MMR": 0, "_id": 5304, "name": "Family", "prestige": 450, "prestige_lvl": 450}, "5569": {"MMR": 0, "_id": 5569, "name": "Gladiators", "prestige": 500, "prestige_lvl": 500}, "5571": {"MMR": 263, "_id": 5571, "name": "The World Trade", "prestige": 5309, "prestige_lvl": 575}, "5634": {"MMR": 925, "_id": 5634, "name": "Crecy & Agincourt", "prestige": 21499, "prestige_lvl": 1725}, "5872": {"MMR": 0, "_id": 5872, "name": "The Horse Thieves\u00ae", "prestige": 625, "prestige_lvl": 625}, "6052": {"MMR": 0, "_id": 6052, "name": "Fight Club", "prestige": 575, "prestige_lvl": 575}, "6053": {"MMR": 341, "_id": 6053, "name": "ENDEAVOUR", "prestige": 7513, "prestige_lvl": 1375}, "6115": {"MMR": 609, "_id": 6115, "name": "CONQUER", "prestige": 16755, "prestige_lvl": 1150}, "6200": {"MMR": 590, "_id": 6200, "name": "Redemption", "prestige": 12515, "prestige_lvl": 1575}, "6225": {"MMR": 348, "_id": 6225, "name": "monty's pythons", "prestige": 7288, "prestige_lvl": 1000}, "6278": {"MMR": 0, "_id": 6278, "name": "Future Builders!", "prestige": 325, "prestige_lvl": 325}, "6387": {"MMR": 564, "_id": 6387, "name": "Eternal Family", "prestige": 11227, "prestige_lvl": 1075}, "6433": {"MMR": 0, "_id": 6433, "name": "FastTrade Guild", "prestige": 1100, "prestige_lvl": 1100}, "6454": {"MMR": 0, "_id": 6454, "name": "The Order of Honour", "prestige": 325, "prestige_lvl": 325}, "6460": {"MMR": 599, "_id": 6460, "name": "Creepy & Apocalyptic", "prestige": 12207, "prestige_lvl": 1425}, "6574": {"MMR": 78, "_id": 6574, "name": "Posuit Dorsum", "prestige": 2029, "prestige_lvl": 625}, "6598": {"MMR": 493, "_id": 6598, "name": "Fellowship Ultima", "prestige": 10024, "prestige_lvl": 1150}, "6650": {"MMR": 0, "_id": 6650, "name": "TheGeorgeCostanzas", "prestige": 925, "prestige_lvl": 925}, "6695": {"MMR": 0, "_id": 6695, "name": "Lady of the Lake", "prestige": 675, "prestige_lvl": 675}, "6699": {"MMR": 576, "_id": 6699, "name": "Trade Union", "prestige": 11602, "prestige_lvl": 1150}, "6827": {"MMR": 0, "_id": 6827, "name": "Events Specialist", "prestige": 375, "prestige_lvl": 375}, "6837": {"MMR": 0, "_id": 6837, "name": "Legends", "prestige": 375, "prestige_lvl": 375}, "6872": {"MMR": 0, "_id": 6872, "name": "Red Castle", "prestige": 550, "prestige_lvl": 550}, "6878": {"MMR": 527, "_id": 6878, "name": "Redemption 2", "prestige": 10611, "prestige_lvl": 1125}, "6890": {"MMR": 737, "_id": 6890, "name": "THE LION KING", "prestige": 14789, "prestige_lvl": 1475}, "6932": {"MMR": 0, "_id": 6932, "name": "The Shadows Reborn", "prestige": 1025, "prestige_lvl": 1025}, "7003": {"MMR": 0, "_id": 7003, "name": "The Perkele", "prestige": 450, "prestige_lvl": 450}, "7010": {"MMR": 604, "_id": 7010, "name": "free trade", "prestige": 12072, "prestige_lvl": 1200}, "7028": {"MMR": 162, "_id": 7028, "name": "Body Count", "prestige": 3716, "prestige_lvl": 800}, "7054": {"MMR": 107, "_id": 7054, "name": "Circus Maximus", "prestige": 2726, "prestige_lvl": 800}, "7091": {"MMR": 486, "_id": 7091, "name": "Thunder & Lightning", "prestige": 9823, "prestige_lvl": 1075}, "7093": {"MMR": 0, "_id": 7093, "name": "Trojan Horde", "prestige": 650, "prestige_lvl": 650}, "7117": {"MMR": 568, "_id": 7117, "name": "\ud83d\udc00Desert Rats\ud83d\udc00", "prestige": 11324, "prestige_lvl": 1100}, "7125": {"MMR": 418, "_id": 7125, "name": "The Red Knights", "prestige": 8574, "prestige_lvl": 1050}, "7129": {"MMR": 0, "_id": 7129, "name": "Soul Drivers", "prestige": 350, "prestige_lvl": 350}, "7157": {"MMR": 394, "_id": 7157, "name": "Jedi", "prestige": 8342, "prestige_lvl": 1250}, "7186": {"MMR": 0, "_id": 7186, "name": "Members Only", "prestige": 375, "prestige_lvl": 375}, "7343": {"MMR": 657, "_id": 7343, "name": "Swords of Freedom", "prestige": 18194, "prestige_lvl": 1500}, "7361": {"MMR": 709, "_id": 7361, "name": "kings of camelot", "prestige": 14609, "prestige_lvl": 1250}, "7393": {"MMR": 0, "_id": 7393, "name": "Amalur", "prestige": 625, "prestige_lvl": 625}, "7403": {"MMR": 0, "_id": 7403, "name": "sert\u00e3 do clan", "prestige": 450, "prestige_lvl": 450}, "7483": {"MMR": 365, "_id": 7483, "name": "Silver Phoenix", "prestige": 7620, "prestige_lvl": 1050}, "7496": {"MMR": 870, "_id": 7496, "name": "Shadow Reapers", "prestige": 25887, "prestige_lvl": 1675}, "7554": {"MMR": 0, "_id": 7554, "name": "Screams of Promises", "prestige": 600, "prestige_lvl": 600}, "7597": {"MMR": 0, "_id": 7597, "name": "Illegal Ninjas", "prestige": 450, "prestige_lvl": 450}, "7723": {"MMR": 586, "_id": 7723, "name": "The Golden Bunch", "prestige": 16692, "prestige_lvl": 1725}, "7738": {"MMR": 752, "_id": 7738, "name": "FLYING KNIGHTS", "prestige": 26115, "prestige_lvl": 1500}, "7781": {"MMR": 0, "_id": 7781, "name": "Merchant of Arvahall", "prestige": 450, "prestige_lvl": 450}, "7856": {"MMR": 388, "_id": 7856, "name": "Vukovi Arvahalla", "prestige": 7909, "prestige_lvl": 925}, "7897": {"MMR": 0, "_id": 7897, "name": "Trade guild", "prestige": 375, "prestige_lvl": 375}, "7907": {"MMR": 0, "_id": 7907, "name": "DOG TAG HUNTER", "prestige": 575, "prestige_lvl": 575}, "7946": {"MMR": 50, "_id": 7946, "name": "Fair Trade", "prestige": 1325, "prestige_lvl": 425}, "7976": {"MMR": 0, "_id": 7976, "name": "The Great A'Tuin", "prestige": 475, "prestige_lvl": 475}, "7989": {"MMR": 306, "_id": 7989, "name": "Eternity", "prestige": 6658, "prestige_lvl": 1150}, "8001": {"MMR": 70, "_id": 8001, "name": "Triple Crown", "prestige": 2060, "prestige_lvl": 800}, "8015": {"MMR": 0, "_id": 8015, "name": "Traders league", "prestige": 450, "prestige_lvl": 450}, "8026": {"MMR": 693, "_id": 8026, "name": "Relaxed", "prestige": 13599, "prestige_lvl": 1125}, "8050": {"MMR": 323, "_id": 8050, "name": "Train Spotters", "prestige": 6589, "prestige_lvl": 775}, "8077": {"MMR": 0, "_id": 8077, "name": "The Dodekatheon", "prestige": 475, "prestige_lvl": 475}, "8160": {"MMR": 0, "_id": 8160, "name": "The Hooded Claw", "prestige": 575, "prestige_lvl": 575}, "8239": {"MMR": 792, "_id": 8239, "name": "Shadow Silver", "prestige": 17988, "prestige_lvl": 1575}, "8268": {"MMR": 0, "_id": 8268, "name": "Stick ya GvG", "prestige": 775, "prestige_lvl": 775}, "8309": {"MMR": 453, "_id": 8309, "name": "Ye Olde Pub & Grill", "prestige": 9154, "prestige_lvl": 1000}, "8362": {"MMR": 121, "_id": 8362, "name": "St. Cuthberts", "prestige": 2903, "prestige_lvl": 725}, "8390": {"MMR": 865, "_id": 8390, "name": "\u00df00TCAMP", "prestige": 17020, "prestige_lvl": 1450}, "8392": {"MMR": 698, "_id": 8392, "name": "whatever", "prestige": 14114, "prestige_lvl": 1550}, "8396": {"MMR": 188, "_id": 8396, "name": "Friends of Justice", "prestige": 4159, "prestige_lvl": 775}, "8406": {"MMR": 0, "_id": 8406, "name": "The Dominion", "prestige": 375, "prestige_lvl": 375}, "8620": {"MMR": 0, "_id": 8620, "name": "** Red Castle **", "prestige": 675, "prestige_lvl": 675}, "8710": {"MMR": 802, "_id": 8710, "name": "ARES", "prestige": 22788, "prestige_lvl": 1375}, "8757": {"MMR": 0, "_id": 8757, "name": "Dark killers", "prestige": 325, "prestige_lvl": 325}, "8967": {"MMR": 499, "_id": 8967, "name": "League of Champions", "prestige": 10007, "prestige_lvl": 1025}, "8988": {"MMR": 668, "_id": 8988, "name": "Iron Fist", "prestige": 13124, "prestige_lvl": 1100}, "8996": {"MMR": 0, "_id": 8996, "name": "ICON", "prestige": 425, "prestige_lvl": 425}, "9099": {"MMR": 0, "_id": 9099, "name": "Prosperity", "prestige": 600, "prestige_lvl": 600}, "9114": {"MMR": 0, "_id": 9114, "name": "Neighborhoodies Too", "prestige": 575, "prestige_lvl": 575}, "9119": {"MMR": 263, "_id": 9119, "name": "THE SUPER GUILD", "prestige": 5259, "prestige_lvl": 525}, "9152": {"MMR": 320, "_id": 9152, "name": "Winterfell Kingdom", "prestige": 6635, "prestige_lvl": 875}, "9158": {"MMR": 458, "_id": 9158, "name": "Enlightenment", "prestige": 9294, "prestige_lvl": 1050}, "9252": {"MMR": 15, "_id": 9252, "name": "Societas Draconis", "prestige": 920, "prestige_lvl": 650}, "9268": {"MMR": 175, "_id": 9268, "name": "H o u s e  VIII", "prestige": 3750, "prestige_lvl": 600}, "9297": {"MMR": 291, "_id": 9297, "name": "\ud83c\uddfb\ud83c\uddf3VietNam\ud83c\uddfb\ud83c\uddf3", "prestige": 6088, "prestige_lvl": 850}, "9367": {"MMR": 0, "_id": 9367, "name": "epir empire", "prestige": 350, "prestige_lvl": 350}, "9378": {"MMR": 375, "_id": 9378, "name": "Lone Ranger", "prestige": 7375, "prestige_lvl": 625}, "9388": {"MMR": 263, "_id": 9388, "name": "The celtic warriors", "prestige": 5359, "prestige_lvl": 625}, "9399": {"MMR": 331, "_id": 9399, "name": "The openers", "prestige": 6858, "prestige_lvl": 900}, "9500": {"MMR": 0, "_id": 9500, "name": "\ud83d\ude07Saints & Sinners\ud83d\ude08", "prestige": 950, "prestige_lvl": 950}, "9527": {"MMR": 1000, "_id": 9527, "name": "GoodFellas Elite", "prestige": 35971, "prestige_lvl": 1700}, "9547": {"MMR": 0, "_id": 9547, "name": "Honour and Trust", "prestige": 875, "prestige_lvl": 875}, "9599": {"MMR": 100, "_id": 9599, "name": "Leopardus pardalis", "prestige": 2500, "prestige_lvl": 700}, "9602": {"MMR": 434, "_id": 9602, "name": "El Lobo", "prestige": 8587, "prestige_lvl": 775}, "9623": {"MMR": 263, "_id": 9623, "name": "Bite Sized Brigade", "prestige": 5309, "prestige_lvl": 575}, "9665": {"MMR": 0, "_id": 9665, "name": "The Hanseatic League", "prestige": 500, "prestige_lvl": 500}, "9676": {"MMR": 64, "_id": 9676, "name": "Zen Knights Of Old", "prestige": 2177, "prestige_lvl": 1025}, "9731": {"MMR": 582, "_id": 9731, "name": "The Norse Gods", "prestige": 11878, "prestige_lvl": 1400}, "9738": {"MMR": 545, "_id": 9738, "name": "CHILLAXED II", "prestige": 11035, "prestige_lvl": 1225}, "9745": {"MMR": 0, "_id": 9745, "name": "New Republic Reborn", "prestige": 425, "prestige_lvl": 425}, "9949": {"MMR": 809, "_id": 9949, "name": "Fellowship of Forge", "prestige": 16248, "prestige_lvl": 1575}, "9996": {"MMR": 0, "_id": 9996, "name": "buholc", "prestige": 375, "prestige_lvl": 375}, "10044": {"MMR": 102, "_id": 10044, "name": "Balkan Legends", "prestige": 2286, "prestige_lvl": 450}, "10066": {"MMR": 176, "_id": 10066, "name": "Rogues of the Grave", "prestige": 3943, "prestige_lvl": 775}, "10165": {"MMR": 0, "_id": 10165, "name": "Inglorious Bastards", "prestige": 475, "prestige_lvl": 475}, "10258": {"MMR": 0, "_id": 10258, "name": "World of one", "prestige": 500, "prestige_lvl": 500}, "10344": {"MMR": 0, "_id": 10344, "name": "Aryans", "prestige": 325, "prestige_lvl": 325}, "10440": {"MMR": 0, "_id": 10440, "name": "Invictus", "prestige": 525, "prestige_lvl": 525}, "10455": {"MMR": 0, "_id": 10455, "name": "shivagon", "prestige": 350, "prestige_lvl": 350}, "10456": {"MMR": 0, "_id": 10456, "name": "Veritas Aequitas", "prestige": 500, "prestige_lvl": 500}, "10469": {"MMR": 0, "_id": 10469, "name": "Riders of Rohan", "prestige": 875, "prestige_lvl": 875}, "10521": {"MMR": 0, "_id": 10521, "name": "Zaika The Great", "prestige": 375, "prestige_lvl": 375}, "10623": {"MMR": 0, "_id": 10623, "name": "Mehan Kingdom", "prestige": 375, "prestige_lvl": 375}, "10697": {"MMR": 0, "_id": 10697, "name": "Zen Haven", "prestige": 350, "prestige_lvl": 350}, "10761": {"MMR": 0, "_id": 10761, "name": "Baruk Khaz\u00e2d!", "prestige": 500, "prestige_lvl": 500}, "10773": {"MMR": 0, "_id": 10773, "name": "Snake", "prestige": 350, "prestige_lvl": 350}, "10782": {"MMR": 0, "_id": 10782, "name": "MungoMohawkers", "prestige": 325, "prestige_lvl": 325}, "10798": {"MMR": 436, "_id": 10798, "name": "The Peaky Blinders", "prestige": 8573, "prestige_lvl": 725}, "10902": {"MMR": 137, "_id": 10902, "name": "Guerilla Warfare", "prestige": 3766, "prestige_lvl": 1300}, "10963": {"MMR": 0, "_id": 10963, "name": "Imperium Aeternam", "prestige": 350, "prestige_lvl": 350}, "11001": {"MMR": 405, "_id": 11001, "name": "Arva Defence Force", "prestige": 8115, "prestige_lvl": 825}, "11021": {"MMR": 785, "_id": 11021, "name": "The Cat Herders \ud83d\ude40", "prestige": 15180, "prestige_lvl": 1050}, "11202": {"MMR": 445, "_id": 11202, "name": "Evolution", "prestige": 10072, "prestige_lvl": 1300}, "11215": {"MMR": 0, "_id": 11215, "name": "BidingTime", "prestige": 425, "prestige_lvl": 425}, "11232": {"MMR": 0, "_id": 11232, "name": "Wariors", "prestige": 325, "prestige_lvl": 325}, "11266": {"MMR": 0, "_id": 11266, "name": "Arvahall Raiders", "prestige": 425, "prestige_lvl": 425}, "11270": {"MMR": 225, "_id": 11270, "name": "The Non-Conformists", "prestige": 5064, "prestige_lvl": 950}, "11292": {"MMR": 542, "_id": 11292, "name": "Respect", "prestige": 10857, "prestige_lvl": 925}, "11439": {"MMR": 0, "_id": 11439, "name": "White Sider", "prestige": 400, "prestige_lvl": 400}, "11507": {"MMR": 513, "_id": 11507, "name": "Arvahall ArchAngels", "prestige": 10484, "prestige_lvl": 1250}, "11574": {"MMR": 0, "_id": 11574, "name": "GHOST", "prestige": 575, "prestige_lvl": 575}, "11576": {"MMR": 238, "_id": 11576, "name": "MAJESTIC", "prestige": 4892, "prestige_lvl": 600}, "11724": {"MMR": 225, "_id": 11724, "name": "Lafayette", "prestige": 4700, "prestige_lvl": 650}, "11797": {"MMR": 0, "_id": 11797, "name": "Babylon5", "prestige": 925, "prestige_lvl": 925}, "11851": {"MMR": 113, "_id": 11851, "name": "Trade for Free", "prestige": 2559, "prestige_lvl": 525}, "11898": {"MMR": 0, "_id": 11898, "name": "Iron Quest", "prestige": 600, "prestige_lvl": 600}, "11908": {"MMR": 572, "_id": 11908, "name": "Tricks_Ltd", "prestige": 11642, "prestige_lvl": 950}, "11969": {"MMR": 0, "_id": 11969, "name": "Freedom Fighters", "prestige": 350, "prestige_lvl": 350}, "11972": {"MMR": 263, "_id": 11972, "name": "Hairbare Bunch", "prestige": 5334, "prestige_lvl": 600}, "12009": {"MMR": 150, "_id": 12009, "name": "Iron Age Kings", "prestige": 3250, "prestige_lvl": 550}, "12066": {"MMR": 831, "_id": 12066, "name": "Warhorse \u2122", "prestige": 24546, "prestige_lvl": 1325}, "12069": {"MMR": 77, "_id": 12069, "name": "Real Fair Trade", "prestige": 2436, "prestige_lvl": 1050}, "12085": {"MMR": 0, "_id": 12085, "name": "Give it a go", "prestige": 325, "prestige_lvl": 325}, "12096": {"MMR": 0, "_id": 12096, "name": "pete", "prestige": 375, "prestige_lvl": 375}, "12307": {"MMR": 0, "_id": 12307, "name": "Green Fingers", "prestige": 625, "prestige_lvl": 625}, "12333": {"MMR": 338, "_id": 12333, "name": "Ferret Tickler", "prestige": 6634, "prestige_lvl": 550}, "12373": {"MMR": 275, "_id": 12373, "name": "Happy Warriors", "prestige": 5800, "prestige_lvl": 850}, "12404": {"MMR": 471, "_id": 12404, "name": "Draconian Empire", "prestige": 9153, "prestige_lvl": 675}, "12434": {"MMR": 482, "_id": 12434, "name": "Homesteaders", "prestige": 10608, "prestige_lvl": 900}, "12478": {"MMR": 0, "_id": 12478, "name": "Reaper69", "prestige": 450, "prestige_lvl": 450}, "12557": {"MMR": 0, "_id": 12557, "name": "Band Of Brothers", "prestige": 450, "prestige_lvl": 450}, "12614": {"MMR": 0, "_id": 12614, "name": "Blood Eagle", "prestige": 325, "prestige_lvl": 325}, "12636": {"MMR": 640, "_id": 12636, "name": "Arthur's Knights", "prestige": 12445, "prestige_lvl": 925}, "12693": {"MMR": 0, "_id": 12693, "name": "New Order", "prestige": 400, "prestige_lvl": 400}, "12730": {"MMR": 0, "_id": 12730, "name": "swords & daggers", "prestige": 425, "prestige_lvl": 425}, "12791": {"MMR": 0, "_id": 12791, "name": "\u03dfThor's Vikings\u03df", "prestige": 325, "prestige_lvl": 325}, "12834": {"MMR": 0, "_id": 12834, "name": "This is a Game!", "prestige": 350, "prestige_lvl": 350}, "12873": {"MMR": 0, "_id": 12873, "name": "Belligerant", "prestige": 500, "prestige_lvl": 500}, "12904": {"MMR": 0, "_id": 12904, "name": "spiderman", "prestige": 425, "prestige_lvl": 425}, "12939": {"MMR": 0, "_id": 12939, "name": "Alliance of Knights", "prestige": 400, "prestige_lvl": 400}, "12951": {"MMR": 0, "_id": 12951, "name": "Vicinus Legends", "prestige": 1000, "prestige_lvl": 1000}, "12957": {"MMR": 88, "_id": 12957, "name": "Thales of Miletus", "prestige": 1934, "prestige_lvl": 350}, "12961": {"MMR": 270, "_id": 12961, "name": "Aliseng", "prestige": 5410, "prestige_lvl": 550}, "13051": {"MMR": 0, "_id": 13051, "name": "Vadars", "prestige": 400, "prestige_lvl": 400}, "13055": {"MMR": 0, "_id": 13055, "name": "BEARSDEN", "prestige": 425, "prestige_lvl": 425}, "13067": {"MMR": 517, "_id": 13067, "name": "Privateers", "prestige": 10500, "prestige_lvl": 1050}, "13088": {"MMR": 0, "_id": 13088, "name": "Knights of Freedom", "prestige": 650, "prestige_lvl": 650}, "13149": {"MMR": 325, "_id": 13149, "name": "' in the Mist", "prestige": 6573, "prestige_lvl": 675}, "13193": {"MMR": 0, "_id": 13193, "name": "Aardvarks of War", "prestige": 350, "prestige_lvl": 350}, "13205": {"MMR": 0, "_id": 13205, "name": "Balkan United \u00ae", "prestige": 750, "prestige_lvl": 750}, "13206": {"MMR": 409, "_id": 13206, "name": "The Lone Wolves", "prestige": 8237, "prestige_lvl": 875}, "13211": {"MMR": 0, "_id": 13211, "name": "all for one", "prestige": 375, "prestige_lvl": 375}, "13212": {"MMR": 93, "_id": 13212, "name": "Guilding", "prestige": 2324, "prestige_lvl": 650}, "13226": {"MMR": 0, "_id": 13226, "name": "madgods", "prestige": 400, "prestige_lvl": 400}, "13230": {"MMR": 296, "_id": 13230, "name": "the great dire wolf", "prestige": 6078, "prestige_lvl": 750}, "13253": {"MMR": 607, "_id": 13253, "name": "zanta", "prestige": 12026, "prestige_lvl": 1100}, "13273": {"MMR": 0, "_id": 13273, "name": "danstk", "prestige": 325, "prestige_lvl": 325}, "13277": {"MMR": 330, "_id": 13277, "name": "Diamond Chasers", "prestige": 6690, "prestige_lvl": 750}, "13296": {"MMR": 363, "_id": 13296, "name": "PSI", "prestige": 6959, "prestige_lvl": 425}, "13327": {"MMR": 0, "_id": 13327, "name": "kings and queens", "prestige": 325, "prestige_lvl": 325}, "13335": {"MMR": 899, "_id": 13335, "name": "Silver Warriors", "prestige": 31709, "prestige_lvl": 1650}, "13359": {"MMR": 188, "_id": 13359, "name": "Valar Dohaeris", "prestige": 3959, "prestige_lvl": 575}, "13370": {"MMR": 100, "_id": 13370, "name": "Arvahall Academy", "prestige": 2375, "prestige_lvl": 575}, "13388": {"MMR": 513, "_id": 13388, "name": "Wild Raiders", "prestige": 10234, "prestige_lvl": 1000}, "13390": {"MMR": 50, "_id": 13390, "name": "Treecat", "prestige": 1475, "prestige_lvl": 575}, "13391": {"MMR": 200, "_id": 13391, "name": "KNIGHT RIDER'S", "prestige": 4100, "prestige_lvl": 500}, "13414": {"MMR": 0, "_id": 13414, "name": "KnightsCross", "prestige": 375, "prestige_lvl": 375}, "13429": {"MMR": 263, "_id": 13429, "name": "SIG", "prestige": 5284, "prestige_lvl": 550}, "13448": {"MMR": 0, "_id": 13448, "name": "Thunder", "prestige": 350, "prestige_lvl": 350}, "13450": {"MMR": 113, "_id": 13450, "name": "\u039b\u03a5\u039a\u039f\u0399", "prestige": 2584, "prestige_lvl": 550}, "13451": {"MMR": 162, "_id": 13451, "name": "Bloody Barons", "prestige": 3616, "prestige_lvl": 700}, "13466": {"MMR": 0, "_id": 13466, "name": "Han Solo", "prestige": 375, "prestige_lvl": 375}, "13507": {"MMR": 0, "_id": 13507, "name": "O A P,s United", "prestige": 375, "prestige_lvl": 375}, "13547": {"MMR": 0, "_id": 13547, "name": "Alpha", "prestige": 525, "prestige_lvl": 525}, "13574": {"MMR": 263, "_id": 13574, "name": "HAPPY DAYS", "prestige": 5484, "prestige_lvl": 750}, "13577": {"MMR": 0, "_id": 13577, "name": "Home Kingdom", "prestige": 375, "prestige_lvl": 375}, "13580": {"MMR": 582, "_id": 13580, "name": "Rogue Traders", "prestige": 11576, "prestige_lvl": 1100}, "13589": {"MMR": 113, "_id": 13589, "name": "Remember the Titans", "prestige": 2509, "prestige_lvl": 475}, "13599": {"MMR": 440, "_id": 13599, "name": "kev n perry go large", "prestige": 9070, "prestige_lvl": 1150}, "13603": {"MMR": 0, "_id": 13603, "name": "The Grimm Reapers", "prestige": 500, "prestige_lvl": 500}, "13611": {"MMR": 0, "_id": 13611, "name": "DRAGON HUNTERS", "prestige": 400, "prestige_lvl": 400}, "13614": {"MMR": 0, "_id": 13614, "name": "THE GLADIATOR", "prestige": 450, "prestige_lvl": 450}, "13616": {"MMR": 790, "_id": 13616, "name": "PRIJATELJI", "prestige": 17429, "prestige_lvl": 1225}, "13623": {"MMR": 0, "_id": 13623, "name": "The Witches Coven", "prestige": 375, "prestige_lvl": 375}, "13639": {"MMR": 0, "_id": 13639, "name": "The Baltic Kingdom", "prestige": 425, "prestige_lvl": 425}, "13649": {"MMR": 0, "_id": 13649, "name": "Order of the Forge", "prestige": 450, "prestige_lvl": 450}, "13660": {"MMR": 0, "_id": 13660, "name": "Master Chief", "prestige": 375, "prestige_lvl": 375}, "13686": {"MMR": 0, "_id": 13686, "name": "Thuggys guild", "prestige": 375, "prestige_lvl": 375}, "13697": {"MMR": 0, "_id": 13697, "name": "Heaven on Earth", "prestige": 375, "prestige_lvl": 375}, "13709": {"MMR": 188, "_id": 13709, "name": "Jim Beam Outlaws", "prestige": 4009, "prestige_lvl": 625}, "13723": {"MMR": 13, "_id": 13723, "name": "Enpire Nation", "prestige": 684, "prestige_lvl": 450}, "13737": {"MMR": 138, "_id": 13737, "name": "Gunners", "prestige": 2834, "prestige_lvl": 350}, "13744": {"MMR": 404, "_id": 13744, "name": "Free Guild", "prestige": 8097, "prestige_lvl": 825}, "13746": {"MMR": 273, "_id": 13746, "name": "Wildfire", "prestige": 6328, "prestige_lvl": 1300}, "13758": {"MMR": 0, "_id": 13758, "name": "The Templar Order", "prestige": 400, "prestige_lvl": 400}, "13759": {"MMR": 0, "_id": 13759, "name": "Hello World", "prestige": 375, "prestige_lvl": 375}, "13767": {"MMR": 16, "_id": 13767, "name": "Raven's Nest", "prestige": 838, "prestige_lvl": 550}, "13786": {"MMR": 313, "_id": 13786, "name": "Nights who say Ni", "prestige": 6134, "prestige_lvl": 500}, "13800": {"MMR": 608, "_id": 13800, "name": "The Tops", "prestige": 11869, "prestige_lvl": 925}, "13801": {"MMR": 0, "_id": 13801, "name": "~~ WOLVERINES ~~", "prestige": 500, "prestige_lvl": 500}, "13815": {"MMR": 0, "_id": 13815, "name": "Furor Celtica", "prestige": 500, "prestige_lvl": 500}, "13824": {"MMR": 0, "_id": 13824, "name": "Fighters and Farmers", "prestige": 650, "prestige_lvl": 650}, "13862": {"MMR": 133, "_id": 13862, "name": "SPECTRUM", "prestige": 3119, "prestige_lvl": 725}, "13907": {"MMR": 0, "_id": 13907, "name": "Kraljevina Srbija", "prestige": 350, "prestige_lvl": 350}, "13909": {"MMR": 461, "_id": 13909, "name": "Anzac", "prestige": 9590, "prestige_lvl": 1100}, "13922": {"MMR": 0, "_id": 13922, "name": "The bleeding boar", "prestige": 500, "prestige_lvl": 500}, "13927": {"MMR": 188, "_id": 13927, "name": "Gods chosen", "prestige": 3709, "prestige_lvl": 325}, "13934": {"MMR": 648, "_id": 13934, "name": "Order of the Phoenix", "prestige": 12614, "prestige_lvl": 950}, "13940": {"MMR": 325, "_id": 13940, "name": "Cabalan Oracles", "prestige": 6400, "prestige_lvl": 550}, "13941": {"MMR": 700, "_id": 13941, "name": "The wise traders", "prestige": 13650, "prestige_lvl": 1050}, "13948": {"MMR": 0, "_id": 13948, "name": "Round Table", "prestige": 575, "prestige_lvl": 575}, "13962": {"MMR": 0, "_id": 13962, "name": "The Casual Guild", "prestige": 500, "prestige_lvl": 500}, "13989": {"MMR": 475, "_id": 13989, "name": "Traders' Union", "prestige": 9275, "prestige_lvl": 725}, "13996": {"MMR": 263, "_id": 13996, "name": "Easy going Guild", "prestige": 5259, "prestige_lvl": 525}, "14000": {"MMR": 113, "_id": 14000, "name": "Blades of Blood", "prestige": 2259, "prestige_lvl": 225}, "14003": {"MMR": 0, "_id": 14003, "name": "The XXX Rider", "prestige": 475, "prestige_lvl": 475}, "14004": {"MMR": 525, "_id": 14004, "name": "Warpigs", "prestige": 10225, "prestige_lvl": 775}, "14031": {"MMR": 275, "_id": 14031, "name": "Iceguild", "prestige": 5550, "prestige_lvl": 600}, "14057": {"MMR": 102, "_id": 14057, "name": "The Regime", "prestige": 2186, "prestige_lvl": 350}, "14066": {"MMR": 0, "_id": 14066, "name": "the old un", "prestige": 475, "prestige_lvl": 475}, "14079": {"MMR": 238, "_id": 14079, "name": "DragonEmpire", "prestige": 4709, "prestige_lvl": 425}, "14086": {"MMR": 225, "_id": 14086, "name": "skye's the limit", "prestige": 4425, "prestige_lvl": 375}, "14091": {"MMR": 430, "_id": 14091, "name": "Pest Controllers", "prestige": 8415, "prestige_lvl": 675}, "14101": {"MMR": 0, "_id": 14101, "name": "Friends of Magpies", "prestige": 325, "prestige_lvl": 325}, "14140": {"MMR": 0, "_id": 14140, "name": "Dragon Slayers", "prestige": 375, "prestige_lvl": 375}, "14142": {"MMR": 477, "_id": 14142, "name": "TIMELORDS", "prestige": 9560, "prestige_lvl": 950}, "14145": {"MMR": 636, "_id": 14145, "name": "Graveyard Shift", "prestige": 12648, "prestige_lvl": 1200}, "14162": {"MMR": 0, "_id": 14162, "name": "Redland Beasts", "prestige": 400, "prestige_lvl": 400}, "14177": {"MMR": 0, "_id": 14177, "name": "Nj's", "prestige": 375, "prestige_lvl": 375}, "14180": {"MMR": 0, "_id": 14180, "name": "Jedi Knights", "prestige": 425, "prestige_lvl": 425}, "14184": {"MMR": 365, "_id": 14184, "name": "Swap shop", "prestige": 7295, "prestige_lvl": 725}, "14185": {"MMR": 0, "_id": 14185, "name": "Middlearth warriors", "prestige": 325, "prestige_lvl": 325}, "14196": {"MMR": 138, "_id": 14196, "name": "Red roses", "prestige": 2934, "prestige_lvl": 450}, "14204": {"MMR": 0, "_id": 14204, "name": "Shield maiden", "prestige": 350, "prestige_lvl": 350}, "14214": {"MMR": 0, "_id": 14214, "name": "The Big Bang Theory", "prestige": 400, "prestige_lvl": 400}, "14215": {"MMR": 451, "_id": 14215, "name": "Lazarus", "prestige": 8868, "prestige_lvl": 750}, "14216": {"MMR": 0, "_id": 14216, "name": "\u25a0\u25a0Secret Butchers\u25a0\u25a0", "prestige": 650, "prestige_lvl": 650}, "14217": {"MMR": 0, "_id": 14217, "name": "Dystopia", "prestige": 400, "prestige_lvl": 400}, "14235": {"MMR": 0, "_id": 14235, "name": "Keating's War", "prestige": 350, "prestige_lvl": 350}, "14239": {"MMR": 0, "_id": 14239, "name": "Wild Pirates", "prestige": 1000, "prestige_lvl": 1000}, "14244": {"MMR": 0, "_id": 14244, "name": "Raiding & Naked", "prestige": 650, "prestige_lvl": 650}, "14258": {"MMR": 0, "_id": 14258, "name": "Zaldivar", "prestige": 350, "prestige_lvl": 350}, "14275": {"MMR": 150, "_id": 14275, "name": "\ud83d\udc8e\ud83d\udc36DIAMOND DOGS\ud83d\udc36\ud83d\udc8e", "prestige": 3275, "prestige_lvl": 575}, "14294": {"MMR": 325, "_id": 14294, "name": "Curiosity", "prestige": 6598, "prestige_lvl": 700}, "14299": {"MMR": 441, "_id": 14299, "name": "RISING PHOENIX", "prestige": 12338, "prestige_lvl": 1200}, "14343": {"MMR": 263, "_id": 14343, "name": "The Goods Store", "prestige": 5134, "prestige_lvl": 400}, "14356": {"MMR": 0, "_id": 14356, "name": "Stingy", "prestige": 350, "prestige_lvl": 350}, "14358": {"MMR": 0, "_id": 14358, "name": "the last crusade", "prestige": 475, "prestige_lvl": 475}, "14366": {"MMR": 0, "_id": 14366, "name": "snake eaters", "prestige": 325, "prestige_lvl": 325}, "14424": {"MMR": 449, "_id": 14424, "name": "The Builders Guild", "prestige": 9107, "prestige_lvl": 1025}, "14462": {"MMR": 188, "_id": 14462, "name": "Wot Am I Doing Here?", "prestige": 4184, "prestige_lvl": 800}, "14483": {"MMR": 0, "_id": 14483, "name": "Tolpuddle Rebels", "prestige": 400, "prestige_lvl": 400}, "14488": {"MMR": 209, "_id": 14488, "name": "Sparta", "prestige": 4362, "prestige_lvl": 600}, "14561": {"MMR": 188, "_id": 14561, "name": "Krazy Kanuk", "prestige": 3859, "prestige_lvl": 475}, "14570": {"MMR": 0, "_id": 14570, "name": "Merlin's Shield", "prestige": 575, "prestige_lvl": 575}, "14573": {"MMR": 0, "_id": 14573, "name": "wolfhound", "prestige": 325, "prestige_lvl": 325}, "14590": {"MMR": 0, "_id": 14590, "name": "KPHTH", "prestige": 500, "prestige_lvl": 500}, "14594": {"MMR": 0, "_id": 14594, "name": "Masters of chrome", "prestige": 350, "prestige_lvl": 350}, "14666": {"MMR": 265, "_id": 14666, "name": "Boleyn Bubbles", "prestige": 5495, "prestige_lvl": 725}, "14671": {"MMR": 0, "_id": 14671, "name": "Bailey Belles", "prestige": 350, "prestige_lvl": 350}, "14678": {"MMR": 0, "_id": 14678, "name": "Guild with no name", "prestige": 500, "prestige_lvl": 500}, "14685": {"MMR": 0, "_id": 14685, "name": "Gallifrey", "prestige": 400, "prestige_lvl": 400}, "14696": {"MMR": 0, "_id": 14696, "name": "Henry & Friends", "prestige": 400, "prestige_lvl": 400}, "14706": {"MMR": 188, "_id": 14706, "name": "ROGUE SLAYERS", "prestige": 3684, "prestige_lvl": 300}, "14728": {"MMR": 0, "_id": 14728, "name": "Tragedy", "prestige": 350, "prestige_lvl": 350}, "14729": {"MMR": 0, "_id": 14729, "name": "Grease monkeys2", "prestige": 450, "prestige_lvl": 450}, "14747": {"MMR": 0, "_id": 14747, "name": "English Elite", "prestige": 325, "prestige_lvl": 325}, "14762": {"MMR": 0, "_id": 14762, "name": "Durham Light", "prestige": 500, "prestige_lvl": 500}, "14787": {"MMR": 0, "_id": 14787, "name": "Diamonds!", "prestige": 475, "prestige_lvl": 475}, "14813": {"MMR": 0, "_id": 14813, "name": "Harry Potter :)", "prestige": 550, "prestige_lvl": 550}, "14828": {"MMR": 75, "_id": 14828, "name": "The Nudist's Guild", "prestige": 1775, "prestige_lvl": 425}, "14830": {"MMR": 0, "_id": 14830, "name": "Bearclan", "prestige": 375, "prestige_lvl": 375}, "14836": {"MMR": 0, "_id": 14836, "name": "The New World", "prestige": 375, "prestige_lvl": 375}, "14837": {"MMR": 150, "_id": 14837, "name": "Eletric Wizard", "prestige": 3225, "prestige_lvl": 525}, "14847": {"MMR": 0, "_id": 14847, "name": "aaa", "prestige": 375, "prestige_lvl": 375}, "14907": {"MMR": 493, "_id": 14907, "name": "Grinders", "prestige": 9649, "prestige_lvl": 775}, "14915": {"MMR": 0, "_id": 14915, "name": "The Gatekeepers", "prestige": 475, "prestige_lvl": 475}, "14940": {"MMR": 275, "_id": 14940, "name": "The legion", "prestige": 5525, "prestige_lvl": 575}, "14946": {"MMR": 263, "_id": 14946, "name": "Against all Odds", "prestige": 5109, "prestige_lvl": 375}, "14972": {"MMR": 0, "_id": 14972, "name": "CASPER", "prestige": 358, "prestige_lvl": 350}, "14983": {"MMR": 0, "_id": 14983, "name": "Uthenera", "prestige": 550, "prestige_lvl": 550}, "14995": {"MMR": 188, "_id": 14995, "name": "radish", "prestige": 3609, "prestige_lvl": 225}, "14998": {"MMR": 625, "_id": 14998, "name": "Resurrection", "prestige": 14724, "prestige_lvl": 1075}, "15018": {"MMR": 0, "_id": 15018, "name": "NS2", "prestige": 550, "prestige_lvl": 550}, "15021": {"MMR": 300, "_id": 15021, "name": "tOaO", "prestige": 5875, "prestige_lvl": 475}, "15045": {"MMR": 590, "_id": 15045, "name": "Flashback", "prestige": 11570, "prestige_lvl": 950}, "15046": {"MMR": 263, "_id": 15046, "name": "ATLANTIS", "prestige": 5609, "prestige_lvl": 875}, "15047": {"MMR": 0, "_id": 15047, "name": "Wonderland", "prestige": 375, "prestige_lvl": 375}, "15051": {"MMR": 0, "_id": 15051, "name": "KeepCalm", "prestige": 400, "prestige_lvl": 400}, "15058": {"MMR": 0, "_id": 15058, "name": "Vanguard", "prestige": 325, "prestige_lvl": 325}, "15068": {"MMR": 525, "_id": 15068, "name": "*Vigilante Justice*", "prestige": 10125, "prestige_lvl": 675}, "15089": {"MMR": 609, "_id": 15089, "name": "SKYY", "prestige": 11993, "prestige_lvl": 1025}, "15098": {"MMR": 263, "_id": 15098, "name": "Freelancers", "prestige": 5034, "prestige_lvl": 300}, "15117": {"MMR": 63, "_id": 15117, "name": "The Call Of Almighty", "prestige": 1634, "prestige_lvl": 500}, "15130": {"MMR": 0, "_id": 15130, "name": "Global Citizen", "prestige": 525, "prestige_lvl": 525}, "15145": {"MMR": 250, "_id": 15145, "name": "EAST WATCH", "prestige": 5125, "prestige_lvl": 625}, "15216": {"MMR": 400, "_id": 15216, "name": "Fox Company", "prestige": 8000, "prestige_lvl": 800}, "15228": {"MMR": 0, "_id": 15228, "name": "uisce beatha", "prestige": 450, "prestige_lvl": 450}, "15258": {"MMR": 0, "_id": 15258, "name": "The Sith", "prestige": 325, "prestige_lvl": 325}, "15273": {"MMR": 0, "_id": 15273, "name": "Rogue", "prestige": 350, "prestige_lvl": 350}, "15312": {"MMR": 475, "_id": 15312, "name": "501st", "prestige": 9215, "prestige_lvl": 625}, "15316": {"MMR": 526, "_id": 15316, "name": "Fair Enough", "prestige": 10493, "prestige_lvl": 1025}, "15321": {"MMR": 263, "_id": 15321, "name": "Euskadi", "prestige": 5134, "prestige_lvl": 400}, "15328": {"MMR": 0, "_id": 15328, "name": "Dilligaf", "prestige": 325, "prestige_lvl": 325}, "15340": {"MMR": 0, "_id": 15340, "name": "Bear Clan", "prestige": 403, "prestige_lvl": 400}, "15344": {"MMR": 625, "_id": 15344, "name": "Prometheus", "prestige": 11908, "prestige_lvl": 650}, "15345": {"MMR": 472, "_id": 15345, "name": "Mariahs", "prestige": 9271, "prestige_lvl": 775}, "15351": {"MMR": 569, "_id": 15351, "name": "English Pride \ud83c\uddec\ud83c\udde7", "prestige": 11292, "prestige_lvl": 1050}, "15359": {"MMR": 0, "_id": 15359, "name": "Twilight Genesis", "prestige": 375, "prestige_lvl": 375}, "15374": {"MMR": 42, "_id": 15374, "name": "1st Degree", "prestige": 1531, "prestige_lvl": 775}, "15395": {"MMR": 263, "_id": 15395, "name": "Old timers", "prestige": 5259, "prestige_lvl": 525}, "15397": {"MMR": 0, "_id": 15397, "name": "weary rest home", "prestige": 325, "prestige_lvl": 325}, "15408": {"MMR": 0, "_id": 15408, "name": "winternigel69", "prestige": 400, "prestige_lvl": 400}, "15415": {"MMR": 211, "_id": 15415, "name": "Moon Lighters", "prestige": 4573, "prestige_lvl": 775}, "15429": {"MMR": 88, "_id": 15429, "name": "TEA PARTY", "prestige": 1984, "prestige_lvl": 400}, "15468": {"MMR": 0, "_id": 15468, "name": "maisonkammerzell", "prestige": 375, "prestige_lvl": 375}, "15482": {"MMR": 263, "_id": 15482, "name": "Happy Go Lucky", "prestige": 5159, "prestige_lvl": 425}, "15498": {"MMR": 0, "_id": 15498, "name": "H.M.*S Loyalty", "prestige": 400, "prestige_lvl": 400}, "15523": {"MMR": 188, "_id": 15523, "name": "Holy grail", "prestige": 3784, "prestige_lvl": 400}, "15550": {"MMR": 418, "_id": 15550, "name": "TrickyTrees", "prestige": 8274, "prestige_lvl": 750}, "15560": {"MMR": 424, "_id": 15560, "name": "Eye-I-Aye", "prestige": 8457, "prestige_lvl": 825}, "15567": {"MMR": 0, "_id": 15567, "name": "The Tinsel Wall", "prestige": 400, "prestige_lvl": 400}, "15576": {"MMR": 234, "_id": 15576, "name": "Spartan massive", "prestige": 4787, "prestige_lvl": 575}, "15584": {"MMR": 250, "_id": 15584, "name": "IndoForger", "prestige": 5100, "prestige_lvl": 600}, "15615": {"MMR": 0, "_id": 15615, "name": "Heart of Avalon", "prestige": 475, "prestige_lvl": 475}, "15642": {"MMR": 263, "_id": 15642, "name": "Blood Riders", "prestige": 5159, "prestige_lvl": 425}, "15648": {"MMR": 398, "_id": 15648, "name": "The Hobbit", "prestige": 8014, "prestige_lvl": 850}, "15662": {"MMR": 560, "_id": 15662, "name": "BOUNTY HUNTERS", "prestige": 12476, "prestige_lvl": 975}, "15668": {"MMR": 152, "_id": 15668, "name": "Forge Fiends", "prestige": 3511, "prestige_lvl": 775}, "15671": {"MMR": 0, "_id": 15671, "name": "Branislav", "prestige": 375, "prestige_lvl": 375}, "15689": {"MMR": 0, "_id": 15689, "name": "PRISIO", "prestige": 475, "prestige_lvl": 475}, "15731": {"MMR": 225, "_id": 15731, "name": "Canadian Warriors", "prestige": 4750, "prestige_lvl": 700}, "15740": {"MMR": 719, "_id": 15740, "name": "Mystic Dragons", "prestige": 13717, "prestige_lvl": 775}, "15746": {"MMR": 37, "_id": 15746, "name": "Urban Militia", "prestige": 1888, "prestige_lvl": 1075}, "15752": {"MMR": 108, "_id": 15752, "name": "Welcome All \ud83d\ude0c", "prestige": 2394, "prestige_lvl": 450}, "15753": {"MMR": 417, "_id": 15753, "name": "R.E.D. 2", "prestige": 8331, "prestige_lvl": 825}, "15774": {"MMR": 250, "_id": 15774, "name": "Green Dragon", "prestige": 5000, "prestige_lvl": 500}, "15777": {"MMR": 0, "_id": 15777, "name": "The House of Bacon", "prestige": 375, "prestige_lvl": 375}, "15778": {"MMR": 498, "_id": 15778, "name": "The Regulars", "prestige": 9789, "prestige_lvl": 825}, "15783": {"MMR": 0, "_id": 15783, "name": "The Dutchmen", "prestige": 550, "prestige_lvl": 550}, "15787": {"MMR": 0, "_id": 15787, "name": "Chillaxin'", "prestige": 625, "prestige_lvl": 625}, "15804": {"MMR": 502, "_id": 15804, "name": "The Magic Monkey", "prestige": 10086, "prestige_lvl": 1050}, "15816": {"MMR": 0, "_id": 15816, "name": "Allied Mercenaries", "prestige": 450, "prestige_lvl": 450}, "15825": {"MMR": 836, "_id": 15825, "name": "League Of Legends", "prestige": 16191, "prestige_lvl": 1125}, "15834": {"MMR": 836, "_id": 15834, "name": "Blood Road 2.0", "prestige": 19351, "prestige_lvl": 1200}, "15870": {"MMR": 404, "_id": 15870, "name": "Legion Of Kings - A", "prestige": 8152, "prestige_lvl": 800}, "15884": {"MMR": 413, "_id": 15884, "name": "The SPARTAN II's", "prestige": 8059, "prestige_lvl": 625}, "15913": {"MMR": 0, "_id": 15913, "name": "Archangels", "prestige": 425, "prestige_lvl": 425}, "15930": {"MMR": 288, "_id": 15930, "name": "Variags", "prestige": 6062, "prestige_lvl": 750}, "15935": {"MMR": 0, "_id": 15935, "name": "Winterfel", "prestige": 425, "prestige_lvl": 425}, "15991": {"MMR": 349, "_id": 15991, "name": "Retired", "prestige": 7182, "prestige_lvl": 900}, "15998": {"MMR": 0, "_id": 15998, "name": "Nottingham Castle", "prestige": 400, "prestige_lvl": 400}, "16004": {"MMR": 200, "_id": 16004, "name": "lions2", "prestige": 4200, "prestige_lvl": 600}, "16007": {"MMR": 275, "_id": 16007, "name": "Trumpville", "prestige": 5500, "prestige_lvl": 550}, "16046": {"MMR": 0, "_id": 16046, "name": "Brotherhood", "prestige": 325, "prestige_lvl": 325}, "16073": {"MMR": 0, "_id": 16073, "name": "Shadow Knights", "prestige": 375, "prestige_lvl": 375}, "16097": {"MMR": 549, "_id": 16097, "name": "THE GOOD SHEPHERDS", "prestige": 10682, "prestige_lvl": 800}, "16102": {"MMR": 0, "_id": 16102, "name": "Great White North", "prestige": 475, "prestige_lvl": 475}, "16107": {"MMR": 0, "_id": 16107, "name": "Dark Jungle", "prestige": 350, "prestige_lvl": 350}, "16108": {"MMR": 0, "_id": 16108, "name": "Companions", "prestige": 325, "prestige_lvl": 325}, "16117": {"MMR": 263, "_id": 16117, "name": "Fawlty Towers", "prestige": 5134, "prestige_lvl": 400}, "16130": {"MMR": 0, "_id": 16130, "name": "Ascension", "prestige": 350, "prestige_lvl": 350}, "16157": {"MMR": 0, "_id": 16157, "name": "Rosa Negra", "prestige": 350, "prestige_lvl": 350}, "16162": {"MMR": 375, "_id": 16162, "name": "The Barbary Raiders", "prestige": 7593, "prestige_lvl": 600}, "16173": {"MMR": 0, "_id": 16173, "name": "Fair trade and aid", "prestige": 350, "prestige_lvl": 350}, "16198": {"MMR": 0, "_id": 16198, "name": "Spartan Warriors", "prestige": 525, "prestige_lvl": 525}, "16211": {"MMR": 263, "_id": 16211, "name": "Just 4fun", "prestige": 5109, "prestige_lvl": 375}, "16242": {"MMR": 175, "_id": 16242, "name": "Avitohol", "prestige": 3675, "prestige_lvl": 525}, "16264": {"MMR": 275, "_id": 16264, "name": "HOUSE OF HIRST", "prestige": 5575, "prestige_lvl": 625}, "16282": {"MMR": 252, "_id": 16282, "name": "The Filthy Casuals", "prestige": 5211, "prestige_lvl": 675}, "16308": {"MMR": 238, "_id": 16308, "name": "Dragons Eyre", "prestige": 4784, "prestige_lvl": 500}, "16310": {"MMR": 406, "_id": 16310, "name": "Super", "prestige": 8008, "prestige_lvl": 700}, "16318": {"MMR": 138, "_id": 16318, "name": "Dances with Lady", "prestige": 2884, "prestige_lvl": 400}, "16325": {"MMR": 0, "_id": 16325, "name": "Dragon lily", "prestige": 425, "prestige_lvl": 425}, "16373": {"MMR": 0, "_id": 16373, "name": "RagMuffins", "prestige": 450, "prestige_lvl": 450}, "16380": {"MMR": 0, "_id": 16380, "name": "Nikola Tesla SRB", "prestige": 575, "prestige_lvl": 575}, "16397": {"MMR": 263, "_id": 16397, "name": "Latvian Partisan's", "prestige": 5634, "prestige_lvl": 800}, "16423": {"MMR": 350, "_id": 16423, "name": "warriors of old", "prestige": 6900, "prestige_lvl": 600}, "16435": {"MMR": 0, "_id": 16435, "name": "Cuddly Kittens", "prestige": 375, "prestige_lvl": 375}, "16437": {"MMR": 0, "_id": 16437, "name": "FIGHT FFS!", "prestige": 525, "prestige_lvl": 525}, "16449": {"MMR": 282, "_id": 16449, "name": "Abandoned Dominion", "prestige": 5626, "prestige_lvl": 550}, "16458": {"MMR": 263, "_id": 16458, "name": "Still thinking !", "prestige": 5234, "prestige_lvl": 500}, "16467": {"MMR": 511, "_id": 16467, "name": "\ud83d\udc3a Hlj\u00f3\u00f0ur \u00dalfur \ud83d\udc3a", "prestige": 10701, "prestige_lvl": 1100}, "16471": {"MMR": 213, "_id": 16471, "name": "WhiteKnights", "prestige": 4159, "prestige_lvl": 325}, "16486": {"MMR": 0, "_id": 16486, "name": "Normal Guild", "prestige": 350, "prestige_lvl": 350}, "16503": {"MMR": 100, "_id": 16503, "name": "Black rose", "prestige": 2325, "prestige_lvl": 525}, "16513": {"MMR": 400, "_id": 16513, "name": "Have Fun", "prestige": 7725, "prestige_lvl": 525}, "16526": {"MMR": 322, "_id": 16526, "name": "\ud83d\udd25Hellz Bellz\ud83d\udd25", "prestige": 6521, "prestige_lvl": 725}, "16527": {"MMR": 623, "_id": 16527, "name": "DRAGONS EYE", "prestige": 12158, "prestige_lvl": 900}, "16578": {"MMR": 65, "_id": 16578, "name": "Knights of Chaos", "prestige": 1595, "prestige_lvl": 425}, "16627": {"MMR": 313, "_id": 16627, "name": "Warden's Of The Sea", "prestige": 6109, "prestige_lvl": 475}, "16649": {"MMR": 150, "_id": 16649, "name": "la pe pe", "prestige": 3150, "prestige_lvl": 450}, "16650": {"MMR": 340, "_id": 16650, "name": "Jade Relic Hunters", "prestige": 6820, "prestige_lvl": 700}, "16661": {"MMR": 749, "_id": 16661, "name": "The Cuckoo's Nest", "prestige": 14919, "prestige_lvl": 1225}, "16685": {"MMR": 457, "_id": 16685, "name": "Happy Hammers", "prestige": 9001, "prestige_lvl": 775}, "16687": {"MMR": 68, "_id": 16687, "name": "Mercers", "prestige": 1524, "prestige_lvl": 300}, "16711": {"MMR": 431, "_id": 16711, "name": "FoE Players", "prestige": 8558, "prestige_lvl": 800}, "16768": {"MMR": 675, "_id": 16768, "name": "The Alliance", "prestige": 12850, "prestige_lvl": 700}, "16783": {"MMR": 0, "_id": 16783, "name": "Maelstrom", "prestige": 575, "prestige_lvl": 575}, "16785": {"MMR": 50, "_id": 16785, "name": "//////", "prestige": 1225, "prestige_lvl": 325}, "16798": {"MMR": 0, "_id": 16798, "name": "No idea", "prestige": 325, "prestige_lvl": 325}, "16816": {"MMR": 375, "_id": 16816, "name": "Skoll's Ragnarok", "prestige": 7425, "prestige_lvl": 675}, "16825": {"MMR": 0, "_id": 16825, "name": "Manchester", "prestige": 375, "prestige_lvl": 375}, "16865": {"MMR": 263, "_id": 16865, "name": "blue star", "prestige": 4984, "prestige_lvl": 250}, "16893": {"MMR": 0, "_id": 16893, "name": "true justice", "prestige": 475, "prestige_lvl": 475}, "16934": {"MMR": 289, "_id": 16934, "name": "\u00b0\u2022 Relic Hunter's \u2022\u00b0", "prestige": 5927, "prestige_lvl": 725}, "16948": {"MMR": 0, "_id": 16948, "name": "Forsaken Swords' Pub", "prestige": 375, "prestige_lvl": 375}, "16949": {"MMR": 350, "_id": 16949, "name": "only god", "prestige": 6850, "prestige_lvl": 550}, "16974": {"MMR": 0, "_id": 16974, "name": "THE ALLIES", "prestige": 375, "prestige_lvl": 375}, "16986": {"MMR": 150, "_id": 16986, "name": "The Firm", "prestige": 3175, "prestige_lvl": 475}, "17027": {"MMR": 0, "_id": 17027, "name": "The Zoo", "prestige": 450, "prestige_lvl": 450}, "17036": {"MMR": 300, "_id": 17036, "name": "the lazy ones", "prestige": 5800, "prestige_lvl": 400}, "17074": {"MMR": 263, "_id": 17074, "name": "The Good Place", "prestige": 5134, "prestige_lvl": 400}, "17091": {"MMR": 0, "_id": 17091, "name": "wicked at heart", "prestige": 450, "prestige_lvl": 450}, "17101": {"MMR": 263, "_id": 17101, "name": "Aussie pride", "prestige": 5134, "prestige_lvl": 400}, "17103": {"MMR": 0, "_id": 17103, "name": "Zarg's Guild", "prestige": 575, "prestige_lvl": 575}, "17131": {"MMR": 430, "_id": 17131, "name": "Swords & Scarecrows", "prestige": 10109, "prestige_lvl": 825}, "17151": {"MMR": 250, "_id": 17151, "name": "Happy", "prestige": 5050, "prestige_lvl": 550}, "17155": {"MMR": 0, "_id": 17155, "name": "Trials", "prestige": 400, "prestige_lvl": 400}, "17170": {"MMR": 78, "_id": 17170, "name": "The Black Sheep.", "prestige": 1679, "prestige_lvl": 275}, "17208": {"MMR": 557, "_id": 17208, "name": "Winter is Coming", "prestige": 10751, "prestige_lvl": 725}, "17213": {"MMR": 0, "_id": 17213, "name": "The 3 musketeers", "prestige": 425, "prestige_lvl": 425}, "17217": {"MMR": 490, "_id": 17217, "name": "Tatsu", "prestige": 9970, "prestige_lvl": 1150}, "17325": {"MMR": 0, "_id": 17325, "name": "The Gathering", "prestige": 400, "prestige_lvl": 400}, "17345": {"MMR": 525, "_id": 17345, "name": "Irony and Diamonds", "prestige": 10000, "prestige_lvl": 550}, "17350": {"MMR": 188, "_id": 17350, "name": "SWORDFISH_69", "prestige": 3684, "prestige_lvl": 300}, "17358": {"MMR": 0, "_id": 17358, "name": "Aussie", "prestige": 400, "prestige_lvl": 400}, "17365": {"MMR": 113, "_id": 17365, "name": "Killer \ud83d\udc45\ud83d\udca6", "prestige": 2259, "prestige_lvl": 225}, "17377": {"MMR": 0, "_id": 17377, "name": "Friendly Fellows", "prestige": 400, "prestige_lvl": 400}, "17380": {"MMR": 350, "_id": 17380, "name": "Area 52 \u00a5", "prestige": 7972, "prestige_lvl": 800}, "17385": {"MMR": 0, "_id": 17385, "name": "MASTERS", "prestige": 400, "prestige_lvl": 400}, "17391": {"MMR": 538, "_id": 17391, "name": "WE ARE ONE!", "prestige": 10534, "prestige_lvl": 850}, "17403": {"MMR": 0, "_id": 17403, "name": "Clan of St George", "prestige": 425, "prestige_lvl": 425}, "17413": {"MMR": 0, "_id": 17413, "name": "shotokan", "prestige": 400, "prestige_lvl": 400}, "17421": {"MMR": 325, "_id": 17421, "name": "Abandoned shores", "prestige": 6425, "prestige_lvl": 575}, "17426": {"MMR": 0, "_id": 17426, "name": "Champions", "prestige": 375, "prestige_lvl": 375}, "17460": {"MMR": 0, "_id": 17460, "name": "The Rangers", "prestige": 375, "prestige_lvl": 375}, "17469": {"MMR": 225, "_id": 17469, "name": "The Hadrian Wallers", "prestige": 4525, "prestige_lvl": 475}, "17478": {"MMR": 0, "_id": 17478, "name": "Green__line", "prestige": 500, "prestige_lvl": 500}, "17491": {"MMR": 375, "_id": 17491, "name": "Rogue Warriors", "prestige": 7625, "prestige_lvl": 875}, "17527": {"MMR": 626, "_id": 17527, "name": "GE Alliance", "prestige": 12068, "prestige_lvl": 800}, "17530": {"MMR": 0, "_id": 17530, "name": "ChunksCastle", "prestige": 350, "prestige_lvl": 350}, "17542": {"MMR": 375, "_id": 17542, "name": "Krypt Crew.", "prestige": 7404, "prestige_lvl": 600}, "17549": {"MMR": 25, "_id": 17549, "name": "Great Trades & Co", "prestige": 950, "prestige_lvl": 500}, "17562": {"MMR": 0, "_id": 17562, "name": "Guild of Mi", "prestige": 600, "prestige_lvl": 600}, "17603": {"MMR": 150, "_id": 17603, "name": "Sparcatus", "prestige": 3225, "prestige_lvl": 525}, "17628": {"MMR": 200, "_id": 17628, "name": "Commonwealth", "prestige": 4150, "prestige_lvl": 550}, "17663": {"MMR": 611, "_id": 17663, "name": "Relic Hunter", "prestige": 11698, "prestige_lvl": 700}, "17677": {"MMR": 0, "_id": 17677, "name": "Aus", "prestige": 450, "prestige_lvl": 450}, "17693": {"MMR": 50, "_id": 17693, "name": "No Demands", "prestige": 1275, "prestige_lvl": 375}, "17709": {"MMR": 325, "_id": 17709, "name": "shadowolf", "prestige": 6475, "prestige_lvl": 625}, "17739": {"MMR": 306, "_id": 17739, "name": "*United*Towns*Army*", "prestige": 6083, "prestige_lvl": 575}, "17762": {"MMR": 0, "_id": 17762, "name": "Orrtek", "prestige": 350, "prestige_lvl": 350}, "17794": {"MMR": 313, "_id": 17794, "name": "GuildForever", "prestige": 6109, "prestige_lvl": 475}, "17885": {"MMR": 68, "_id": 17885, "name": "Little Devils", "prestige": 1524, "prestige_lvl": 300}, "17898": {"MMR": 150, "_id": 17898, "name": "PigsMightFly", "prestige": 3250, "prestige_lvl": 550}, "17915": {"MMR": 0, "_id": 17915, "name": "MethodInTheMadness", "prestige": 668, "prestige_lvl": 650}, "17941": {"MMR": 0, "_id": 17941, "name": "RISING  PHOENIX", "prestige": 375, "prestige_lvl": 375}, "17985": {"MMR": 125, "_id": 17985, "name": "\u0411\u044a\u043b\u0433\u0430\u0440\u0438\u044f Bulgaria", "prestige": 2800, "prestige_lvl": 550}, "17989": {"MMR": 0, "_id": 17989, "name": "Moose Meat", "prestige": 325, "prestige_lvl": 325}, "18016": {"MMR": 0, "_id": 18016, "name": "GEwar", "prestige": 575, "prestige_lvl": 575}, "18028": {"MMR": 0, "_id": 18028, "name": "senior fun lovers", "prestige": 400, "prestige_lvl": 400}, "18044": {"MMR": 175, "_id": 18044, "name": "BG MASTERS", "prestige": 3700, "prestige_lvl": 550}, "18047": {"MMR": 338, "_id": 18047, "name": "Elvendale", "prestige": 6584, "prestige_lvl": 500}, "18058": {"MMR": 400, "_id": 18058, "name": "CCCP", "prestige": 7800, "prestige_lvl": 600}, "18067": {"MMR": 0, "_id": 18067, "name": "Council of Rulers", "prestige": 350, "prestige_lvl": 350}, "18068": {"MMR": 103, "_id": 18068, "name": "CharmOffensive", "prestige": 2254, "prestige_lvl": 400}, "18100": {"MMR": 0, "_id": 18100, "name": "Diamond Farms", "prestige": 425, "prestige_lvl": 425}, "18119": {"MMR": 156, "_id": 18119, "name": "relaxed approach", "prestige": 3433, "prestige_lvl": 625}, "18130": {"MMR": 0, "_id": 18130, "name": "Sons of Thor", "prestige": 425, "prestige_lvl": 425}, "18133": {"MMR": 715, "_id": 18133, "name": "Dragon Inferno", "prestige": 13670, "prestige_lvl": 800}, "18168": {"MMR": 549, "_id": 18168, "name": "The Balance of Power", "prestige": 10607, "prestige_lvl": 725}, "18193": {"MMR": 50, "_id": 18193, "name": "Resolute Remnant", "prestige": 1400, "prestige_lvl": 500}, "18267": {"MMR": 400, "_id": 18267, "name": "Lhasa", "prestige": 7800, "prestige_lvl": 600}, "18315": {"MMR": 350, "_id": 18315, "name": "The Lodge \ud83c\udf7e", "prestige": 6925, "prestige_lvl": 625}, "18396": {"MMR": 0, "_id": 18396, "name": "half moon", "prestige": 375, "prestige_lvl": 375}, "18432": {"MMR": 388, "_id": 18432, "name": "Bundaleer Heights", "prestige": 7534, "prestige_lvl": 550}, "18438": {"MMR": 0, "_id": 18438, "name": "Apex Predators", "prestige": 350, "prestige_lvl": 350}, "18451": {"MMR": 0, "_id": 18451, "name": "Damascan Horde", "prestige": 625, "prestige_lvl": 625}, "18461": {"MMR": 0, "_id": 18461, "name": "Skerat's trail blaze", "prestige": 325, "prestige_lvl": 325}, "18483": {"MMR": 575, "_id": 18483, "name": "Ladies of the Forge", "prestige": 10975, "prestige_lvl": 625}, "18493": {"MMR": 0, "_id": 18493, "name": "Quo Vadis", "prestige": 375, "prestige_lvl": 375}, "18521": {"MMR": 100, "_id": 18521, "name": "Expeditionary Force", "prestige": 2225, "prestige_lvl": 425}, "18554": {"MMR": 250, "_id": 18554, "name": "Lost Souls \ud83d\udc7b", "prestige": 5150, "prestige_lvl": 650}, "18576": {"MMR": 0, "_id": 18576, "name": "Own Pace", "prestige": 325, "prestige_lvl": 325}, "18579": {"MMR": 200, "_id": 18579, "name": "Milluna", "prestige": 4050, "prestige_lvl": 450}, "18588": {"MMR": 263, "_id": 18588, "name": "The Circle", "prestige": 5084, "prestige_lvl": 350}, "18626": {"MMR": 0, "_id": 18626, "name": "Canada Rocks", "prestige": 375, "prestige_lvl": 375}, "18638": {"MMR": 212, "_id": 18638, "name": "All or nothing", "prestige": 4491, "prestige_lvl": 675}, "18646": {"MMR": 0, "_id": 18646, "name": "The Szgany", "prestige": 650, "prestige_lvl": 650}, "18683": {"MMR": 45, "_id": 18683, "name": "Thailand", "prestige": 1185, "prestige_lvl": 375}, "18699": {"MMR": 0, "_id": 18699, "name": "\ud83c\udf3cDream Meadow\ud83c\udf3c", "prestige": 425, "prestige_lvl": 425}, "18720": {"MMR": 575, "_id": 18720, "name": "Rebel Waltz", "prestige": 10950, "prestige_lvl": 600}, "18737": {"MMR": 0, "_id": 18737, "name": "snafu", "prestige": 375, "prestige_lvl": 375}, "18757": {"MMR": 377, "_id": 18757, "name": "The diamonds", "prestige": 7536, "prestige_lvl": 750}, "18770": {"MMR": 331, "_id": 18770, "name": "Men & Monsters", "prestige": 6683, "prestige_lvl": 725}, "18779": {"MMR": 400, "_id": 18779, "name": "Light Bringers", "prestige": 7775, "prestige_lvl": 575}, "18805": {"MMR": 331, "_id": 18805, "name": "ASTURIAS", "prestige": 6826, "prestige_lvl": 700}, "18823": {"MMR": 188, "_id": 18823, "name": "HRH Wookie", "prestige": 3884, "prestige_lvl": 500}, "18856": {"MMR": 200, "_id": 18856, "name": "MMI", "prestige": 4125, "prestige_lvl": 525}, "18902": {"MMR": 0, "_id": 18902, "name": "davesden", "prestige": 350, "prestige_lvl": 350}, "18907": {"MMR": 277, "_id": 18907, "name": "Chosen Few", "prestige": 5686, "prestige_lvl": 700}, "18943": {"MMR": 453, "_id": 18943, "name": "Srbija NS", "prestige": 9085, "prestige_lvl": 675}, "18951": {"MMR": 0, "_id": 18951, "name": "Black Parade", "prestige": 475, "prestige_lvl": 475}, "18965": {"MMR": 150, "_id": 18965, "name": "forest", "prestige": 3225, "prestige_lvl": 525}, "18982": {"MMR": 325, "_id": 18982, "name": "Jagged", "prestige": 6400, "prestige_lvl": 550}, "18983": {"MMR": 591, "_id": 18983, "name": "Samsara", "prestige": 12013, "prestige_lvl": 1375}, "19005": {"MMR": 400, "_id": 19005, "name": "Death", "prestige": 7980, "prestige_lvl": 650}, "19015": {"MMR": 670, "_id": 19015, "name": "Trade Republic", "prestige": 12910, "prestige_lvl": 850}, "19031": {"MMR": 263, "_id": 19031, "name": "Light", "prestige": 5184, "prestige_lvl": 450}, "19043": {"MMR": 0, "_id": 19043, "name": "Killuminati Empire", "prestige": 350, "prestige_lvl": 350}, "19049": {"MMR": 263, "_id": 19049, "name": "Don Pedro", "prestige": 5184, "prestige_lvl": 450}, "19068": {"MMR": 0, "_id": 19068, "name": "Resident Evil", "prestige": 775, "prestige_lvl": 775}, "19070": {"MMR": 0, "_id": 19070, "name": "WeDaOne1", "prestige": 375, "prestige_lvl": 375}, "19103": {"MMR": 0, "_id": 19103, "name": "justforme", "prestige": 425, "prestige_lvl": 425}, "19112": {"MMR": 308, "_id": 19112, "name": "Avenging Angels", "prestige": 6294, "prestige_lvl": 750}, "19152": {"MMR": 3, "_id": 19152, "name": "mealone", "prestige": 429, "prestige_lvl": 375}, "19205": {"MMR": 0, "_id": 19205, "name": "EXO WRAITH", "prestige": 600, "prestige_lvl": 600}, "19213": {"MMR": 450, "_id": 19213, "name": "Fighters club", "prestige": 8700, "prestige_lvl": 600}, "19275": {"MMR": 250, "_id": 19275, "name": "nac\ud83c\udf7bmac\ud83e\udd42feegles\ud83d\udc4a", "prestige": 5025, "prestige_lvl": 525}, "19328": {"MMR": 525, "_id": 19328, "name": "BroArmy", "prestige": 10025, "prestige_lvl": 575}, "19353": {"MMR": 0, "_id": 19353, "name": "Guilded Lily", "prestige": 375, "prestige_lvl": 375}, "19368": {"MMR": 0, "_id": 19368, "name": "FIRESOFHELL666", "prestige": 375, "prestige_lvl": 375}, "19392": {"MMR": 360, "_id": 19392, "name": "Arvahall Alliance", "prestige": 7130, "prestige_lvl": 650}, "19396": {"MMR": 375, "_id": 19396, "name": "Fletchers", "prestige": 7325, "prestige_lvl": 575}, "19454": {"MMR": 213, "_id": 19454, "name": "THE BLACK DEATH", "prestige": 4534, "prestige_lvl": 700}, "19472": {"MMR": 100, "_id": 19472, "name": "Savage Poodle Eye", "prestige": 2300, "prestige_lvl": 500}, "19527": {"MMR": 145, "_id": 19527, "name": "Gates of Hell", "prestige": 3210, "prestige_lvl": 600}, "19602": {"MMR": 0, "_id": 19602, "name": "Golgotha", "prestige": 475, "prestige_lvl": 475}, "19664": {"MMR": 669, "_id": 19664, "name": "UNITED NATIONS", "prestige": 16001, "prestige_lvl": 875}, "19712": {"MMR": 43, "_id": 19712, "name": "Balkan Alliance", "prestige": 1324, "prestige_lvl": 550}, "19756": {"MMR": 244, "_id": 19756, "name": "Revolution", "prestige": 5167, "prestige_lvl": 775}, "19774": {"MMR": 0, "_id": 19774, "name": "bulgarian1", "prestige": 400, "prestige_lvl": 400}, "19777": {"MMR": 0, "_id": 19777, "name": "Gigatrek", "prestige": 425, "prestige_lvl": 425}, "19780": {"MMR": 416, "_id": 19780, "name": "Rising Force", "prestige": 8163, "prestige_lvl": 675}, "19796": {"MMR": 0, "_id": 19796, "name": "Kiwi", "prestige": 350, "prestige_lvl": 350}, "19834": {"MMR": 525, "_id": 19834, "name": "Ellcos2", "prestige": 10025, "prestige_lvl": 575}, "19850": {"MMR": 0, "_id": 19850, "name": "Hadas II.", "prestige": 475, "prestige_lvl": 475}, "19854": {"MMR": 163, "_id": 19854, "name": "Loyalsteel", "prestige": 3359, "prestige_lvl": 425}, "19858": {"MMR": 425, "_id": 19858, "name": "Zombieland", "prestige": 8200, "prestige_lvl": 550}, "19890": {"MMR": 0, "_id": 19890, "name": "Chaos", "prestige": 600, "prestige_lvl": 600}, "19912": {"MMR": 175, "_id": 19912, "name": "Zgubi", "prestige": 3700, "prestige_lvl": 550}, "19974": {"MMR": 0, "_id": 19974, "name": "Diamondies", "prestige": 423, "prestige_lvl": 375}, "19984": {"MMR": 0, "_id": 19984, "name": "The Black Watch", "prestige": 375, "prestige_lvl": 375}, "19998": {"MMR": 0, "_id": 19998, "name": "The Stronghold", "prestige": 525, "prestige_lvl": 525}, "20021": {"MMR": 175, "_id": 20021, "name": "LoneWolf", "prestige": 3720, "prestige_lvl": 550}, "20066": {"MMR": 225, "_id": 20066, "name": "Nights Watch", "prestige": 4475, "prestige_lvl": 425}, "20092": {"MMR": 0, "_id": 20092, "name": "Midgar warriors", "prestige": 475, "prestige_lvl": 475}, "20136": {"MMR": 72, "_id": 20136, "name": "Shaken not stirred", "prestige": 1646, "prestige_lvl": 350}, "20145": {"MMR": 7, "_id": 20145, "name": "SOLO_ARVAHAL", "prestige": 701, "prestige_lvl": 575}, "20155": {"MMR": 102, "_id": 20155, "name": "Bardisha", "prestige": 2211, "prestige_lvl": 375}, "20157": {"MMR": 150, "_id": 20157, "name": "Kelantan new", "prestige": 2925, "prestige_lvl": 225}, "20196": {"MMR": 625, "_id": 20196, "name": "Villiers", "prestige": 12102, "prestige_lvl": 650}, "20239": {"MMR": 78, "_id": 20239, "name": "Marching on together", "prestige": 1729, "prestige_lvl": 325}, "20268": {"MMR": 13, "_id": 20268, "name": "Aetolian League", "prestige": 759, "prestige_lvl": 525}, "20277": {"MMR": 0, "_id": 20277, "name": "Inheritance Guild", "prestige": 375, "prestige_lvl": 375}, "20299": {"MMR": 760, "_id": 20299, "name": "GFE Academy", "prestige": 15663, "prestige_lvl": 1325}, "20300": {"MMR": 113, "_id": 20300, "name": "nemesis", "prestige": 2384, "prestige_lvl": 350}, "20307": {"MMR": 0, "_id": 20307, "name": "Masons", "prestige": 375, "prestige_lvl": 375}, "20361": {"MMR": 13, "_id": 20361, "name": "TheWhisperingEye", "prestige": 459, "prestige_lvl": 225}, "20375": {"MMR": 76, "_id": 20375, "name": "Kamikaze Penguins", "prestige": 2293, "prestige_lvl": 925}, "20416": {"MMR": 433, "_id": 20416, "name": "Contra Mundum", "prestige": 8819, "prestige_lvl": 1025}, "20445": {"MMR": 102, "_id": 20445, "name": "Make a Killing!", "prestige": 2361, "prestige_lvl": 525}, "20454": {"MMR": 363, "_id": 20454, "name": "Ellerslie", "prestige": 7134, "prestige_lvl": 600}, "20478": {"MMR": 238, "_id": 20478, "name": "The Beatnicks", "prestige": 4684, "prestige_lvl": 400}, "20479": {"MMR": 0, "_id": 20479, "name": "Mani", "prestige": 475, "prestige_lvl": 475}, "20485": {"MMR": 228, "_id": 20485, "name": "QQQ", "prestige": 4654, "prestige_lvl": 550}, "20526": {"MMR": 0, "_id": 20526, "name": "MERCS-4-HIRE", "prestige": 515, "prestige_lvl": 475}, "20611": {"MMR": 127, "_id": 20611, "name": "Face Crushers", "prestige": 2761, "prestige_lvl": 475}, "20616": {"MMR": 0, "_id": 20616, "name": "Chillypalmer", "prestige": 375, "prestige_lvl": 375}, "20633": {"MMR": 0, "_id": 20633, "name": "No requirement", "prestige": 350, "prestige_lvl": 350}, "20644": {"MMR": 296, "_id": 20644, "name": "The Royal Hobbits", "prestige": 6253, "prestige_lvl": 925}, "20648": {"MMR": 90, "_id": 20648, "name": "35 Knots", "prestige": 2095, "prestige_lvl": 475}, "20692": {"MMR": 100, "_id": 20692, "name": "Necromongers", "prestige": 2375, "prestige_lvl": 575}, "20715": {"MMR": 0, "_id": 20715, "name": "Lounge Lizards", "prestige": 400, "prestige_lvl": 400}, "20717": {"MMR": 150, "_id": 20717, "name": "Erebus' Souls", "prestige": 3200, "prestige_lvl": 500}, "20740": {"MMR": 200, "_id": 20740, "name": "Roundtable", "prestige": 4175, "prestige_lvl": 575}, "20758": {"MMR": 225, "_id": 20758, "name": "Way of the dragon", "prestige": 4450, "prestige_lvl": 400}, "20800": {"MMR": 0, "_id": 20800, "name": "Me and your mom", "prestige": 670, "prestige_lvl": 550}, "20841": {"MMR": 0, "_id": 20841, "name": "KOPM", "prestige": 450, "prestige_lvl": 450}, "20854": {"MMR": 413, "_id": 20854, "name": "Planetary Alliance", "prestige": 8034, "prestige_lvl": 600}, "20869": {"MMR": 0, "_id": 20869, "name": "Dem Boys", "prestige": 350, "prestige_lvl": 350}, "20889": {"MMR": 225, "_id": 20889, "name": "1 men show", "prestige": 4275, "prestige_lvl": 225}, "20906": {"MMR": 288, "_id": 20906, "name": "The Family", "prestige": 5734, "prestige_lvl": 550}, "20980": {"MMR": 0, "_id": 20980, "name": "Warmart", "prestige": 375, "prestige_lvl": 375}, "20993": {"MMR": 225, "_id": 20993, "name": "The Renegades", "prestige": 4575, "prestige_lvl": 525}, "21012": {"MMR": 501, "_id": 21012, "name": "Forward Together", "prestige": 9768, "prestige_lvl": 750}, "21054": {"MMR": 15, "_id": 21054, "name": "breaking bad", "prestige": 745, "prestige_lvl": 475}, "21058": {"MMR": 275, "_id": 21058, "name": "knock out", "prestige": 5525, "prestige_lvl": 575}, "21060": {"MMR": 970, "_id": 21060, "name": "Elysium", "prestige": 23286, "prestige_lvl": 1200}, "21073": {"MMR": 251, "_id": 21073, "name": "Paper Tigers", "prestige": 5193, "prestige_lvl": 675}, "21083": {"MMR": 65, "_id": 21083, "name": "VALENT", "prestige": 1595, "prestige_lvl": 425}, "21104": {"MMR": 0, "_id": 21104, "name": "MeMeMe", "prestige": 575, "prestige_lvl": 575}, "21106": {"MMR": 375, "_id": 21106, "name": "The Grateful Dead", "prestige": 7325, "prestige_lvl": 575}, "21108": {"MMR": 68, "_id": 21108, "name": "TRAKIANS", "prestige": 1549, "prestige_lvl": 325}, "21125": {"MMR": 150, "_id": 21125, "name": "Kronstadt", "prestige": 3150, "prestige_lvl": 450}, "21170": {"MMR": 263, "_id": 21170, "name": "Kezzas,Killers", "prestige": 5109, "prestige_lvl": 375}, "21203": {"MMR": 250, "_id": 21203, "name": "The only one", "prestige": 5100, "prestige_lvl": 600}, "21316": {"MMR": 440, "_id": 21316, "name": "Ren's Place", "prestige": 8520, "prestige_lvl": 600}, "21329": {"MMR": 573, "_id": 21329, "name": "The Mocking Jay", "prestige": 11114, "prestige_lvl": 800}, "21345": {"MMR": 475, "_id": 21345, "name": "Scotland the Bravest", "prestige": 9175, "prestige_lvl": 625}, "21354": {"MMR": 200, "_id": 21354, "name": "Polska gola", "prestige": 4050, "prestige_lvl": 450}, "21357": {"MMR": 463, "_id": 21357, "name": "Legion of Doom", "prestige": 9034, "prestige_lvl": 700}, "21367": {"MMR": 188, "_id": 21367, "name": "Templars Guild", "prestige": 3759, "prestige_lvl": 375}, "21379": {"MMR": 192, "_id": 21379, "name": "Lycan 2", "prestige": 3856, "prestige_lvl": 400}, "21384": {"MMR": 375, "_id": 21384, "name": "Mist", "prestige": 7300, "prestige_lvl": 550}, "21385": {"MMR": 113, "_id": 21385, "name": "Wolves of Winterfell", "prestige": 2284, "prestige_lvl": 250}, "21454": {"MMR": 0, "_id": 21454, "name": "Breach of the Peace", "prestige": 600, "prestige_lvl": 600}, "21470": {"MMR": 0, "_id": 21470, "name": "Gaia", "prestige": 500, "prestige_lvl": 500}, "21484": {"MMR": 475, "_id": 21484, "name": "**Carpe Diem**", "prestige": 9125, "prestige_lvl": 575}, "21530": {"MMR": 110, "_id": 21530, "name": "\u0413\u043b\u0430\u0432\u043d\u0438", "prestige": 2505, "prestige_lvl": 525}, "21538": {"MMR": 263, "_id": 21538, "name": "Harmonious", "prestige": 5034, "prestige_lvl": 300}, "21551": {"MMR": 225, "_id": 21551, "name": "SouthernCross Allies", "prestige": 4625, "prestige_lvl": 575}, "21586": {"MMR": 188, "_id": 21586, "name": "Mexico", "prestige": 3659, "prestige_lvl": 275}, "21604": {"MMR": 325, "_id": 21604, "name": "Gumbo Jumbo", "prestige": 6350, "prestige_lvl": 500}, "21692": {"MMR": 0, "_id": 21692, "name": "Dragon Warriors", "prestige": 400, "prestige_lvl": 400}, "21714": {"MMR": 0, "_id": 21714, "name": "Critical Mass", "prestige": 425, "prestige_lvl": 425}, "21743": {"MMR": 98, "_id": 21743, "name": "Daydream", "prestige": 2189, "prestige_lvl": 425}, "21754": {"MMR": 450, "_id": 21754, "name": "Gorillaz", "prestige": 8675, "prestige_lvl": 575}, "21785": {"MMR": 269, "_id": 21785, "name": "Groovy Groovers 3", "prestige": 5592, "prestige_lvl": 750}, "21819": {"MMR": 263, "_id": 21819, "name": "The Holding Pen", "prestige": 5109, "prestige_lvl": 375}, "21829": {"MMR": 348, "_id": 21829, "name": "/......./", "prestige": 7014, "prestige_lvl": 750}, "21855": {"MMR": 175, "_id": 21855, "name": "MONOPOLY", "prestige": 3705, "prestige_lvl": 525}, "21876": {"MMR": 88, "_id": 21876, "name": "Yorks Vikings", "prestige": 1934, "prestige_lvl": 350}, "21878": {"MMR": 660, "_id": 21878, "name": "Dobby's sock", "prestige": 12798, "prestige_lvl": 850}, "21897": {"MMR": 375, "_id": 21897, "name": "IDK", "prestige": 7300, "prestige_lvl": 550}, "21905": {"MMR": 325, "_id": 21905, "name": "Everlong", "prestige": 6400, "prestige_lvl": 550}, "21906": {"MMR": 475, "_id": 21906, "name": "LangNgheo", "prestige": 9175, "prestige_lvl": 625}, "21932": {"MMR": 75, "_id": 21932, "name": "The Twisted Crew", "prestige": 1800, "prestige_lvl": 450}, "21947": {"MMR": 263, "_id": 21947, "name": "Espa\u00edn", "prestige": 5234, "prestige_lvl": 500}, "21955": {"MMR": 68, "_id": 21955, "name": "Cr33d", "prestige": 1674, "prestige_lvl": 450}, "21970": {"MMR": 188, "_id": 21970, "name": "playanyway", "prestige": 3809, "prestige_lvl": 425}, "22012": {"MMR": 40, "_id": 22012, "name": "Minimus", "prestige": 1295, "prestige_lvl": 575}, "22014": {"MMR": 263, "_id": 22014, "name": "Judia Peoples Front", "prestige": 5059, "prestige_lvl": 325}, "22025": {"MMR": 525, "_id": 22025, "name": "Diesel's Raiders", "prestige": 10125, "prestige_lvl": 675}, "22053": {"MMR": 175, "_id": 22053, "name": "Quick guild", "prestige": 3700, "prestige_lvl": 550}, "22085": {"MMR": 500, "_id": 22085, "name": "The Chilled Guild", "prestige": 9650, "prestige_lvl": 650}, "22116": {"MMR": 200, "_id": 22116, "name": "Pepeloters", "prestige": 4100, "prestige_lvl": 500}, "22154": {"MMR": 0, "_id": 22154, "name": "Ludus Batiatus", "prestige": 400, "prestige_lvl": 400}, "22171": {"MMR": 167, "_id": 22171, "name": "The Last Stand", "prestige": 3581, "prestige_lvl": 575}, "22182": {"MMR": 0, "_id": 22182, "name": "The Pachas", "prestige": 375, "prestige_lvl": 375}, "22191": {"MMR": 0, "_id": 22191, "name": "G.E", "prestige": 473, "prestige_lvl": 425}, "22210": {"MMR": 325, "_id": 22210, "name": "The Vanguard", "prestige": 6425, "prestige_lvl": 575}, "22211": {"MMR": 275, "_id": 22211, "name": "LDK", "prestige": 5500, "prestige_lvl": 550}, "22244": {"MMR": 137, "_id": 22244, "name": "Monkey's King", "prestige": 2991, "prestige_lvl": 525}, "22246": {"MMR": 450, "_id": 22246, "name": "Acumen guardians", "prestige": 8700, "prestige_lvl": 600}, "22267": {"MMR": 425, "_id": 22267, "name": "singularis", "prestige": 8175, "prestige_lvl": 525}, "22283": {"MMR": 425, "_id": 22283, "name": "Wolf Pack", "prestige": 8175, "prestige_lvl": 525}, "22284": {"MMR": 200, "_id": 22284, "name": "Nitewatch", "prestige": 4050, "prestige_lvl": 450}, "22288": {"MMR": 125, "_id": 22288, "name": "Zerozi", "prestige": 2725, "prestige_lvl": 475}, "22302": {"MMR": 125, "_id": 22302, "name": "W.W.W.", "prestige": 2800, "prestige_lvl": 550}, "22314": {"MMR": 679, "_id": 22314, "name": "Social Watchman", "prestige": 12847, "prestige_lvl": 625}, "22343": {"MMR": 78, "_id": 22343, "name": "Otaku's Guild", "prestige": 1729, "prestige_lvl": 325}, "22352": {"MMR": 691, "_id": 22352, "name": "beer and bacon", "prestige": 14901, "prestige_lvl": 800}, "22363": {"MMR": 138, "_id": 22363, "name": "Terriers 11", "prestige": 2859, "prestige_lvl": 375}, "22373": {"MMR": 270, "_id": 22373, "name": "TimeLoop", "prestige": 5485, "prestige_lvl": 625}, "22398": {"MMR": 300, "_id": 22398, "name": "We the North", "prestige": 5925, "prestige_lvl": 525}, "22464": {"MMR": 88, "_id": 22464, "name": "mikes133", "prestige": 1834, "prestige_lvl": 250}, "22491": {"MMR": 350, "_id": 22491, "name": "Highway 66", "prestige": 6850, "prestige_lvl": 550}, "22516": {"MMR": 113, "_id": 22516, "name": "***THE DARK SIDE***", "prestige": 2559, "prestige_lvl": 525}, "22531": {"MMR": 125, "_id": 22531, "name": "Xenomorphs", "prestige": 2775, "prestige_lvl": 525}, "22533": {"MMR": 0, "_id": 22533, "name": "Grilled Cheese", "prestige": 350, "prestige_lvl": 350}, "22547": {"MMR": 188, "_id": 22547, "name": "Conquer Squad\ud83d\udc51", "prestige": 3784, "prestige_lvl": 400}, "22597": {"MMR": 68, "_id": 22597, "name": "Smrtihlav", "prestige": 1599, "prestige_lvl": 375}, "22631": {"MMR": 500, "_id": 22631, "name": "Game of Arcs", "prestige": 9575, "prestige_lvl": 575}, "22656": {"MMR": 363, "_id": 22656, "name": "GAMETEST", "prestige": 6934, "prestige_lvl": 400}, "22661": {"MMR": 250, "_id": 22661, "name": "pool of life", "prestige": 5050, "prestige_lvl": 550}, "22751": {"MMR": 125, "_id": 22751, "name": "The Chook Shed", "prestige": 2825, "prestige_lvl": 575}, "22764": {"MMR": 263, "_id": 22764, "name": "Travelers", "prestige": 5059, "prestige_lvl": 325}, "22770": {"MMR": 0, "_id": 22770, "name": "The Trade Empire", "prestige": 375, "prestige_lvl": 375}, "22794": {"MMR": 0, "_id": 22794, "name": "Expedition Force", "prestige": 350, "prestige_lvl": 350}, "22821": {"MMR": 0, "_id": 22821, "name": "Anivad \ud83d\udc96", "prestige": 375, "prestige_lvl": 375}, "22853": {"MMR": 253, "_id": 22853, "name": "20 warriors", "prestige": 5129, "prestige_lvl": 575}, "22865": {"MMR": 200, "_id": 22865, "name": "Libertas A", "prestige": 4150, "prestige_lvl": 550}, "22872": {"MMR": 200, "_id": 22872, "name": "A Guild of One", "prestige": 4075, "prestige_lvl": 475}, "22886": {"MMR": 651, "_id": 22886, "name": "Marauders", "prestige": 16693, "prestige_lvl": 925}, "22905": {"MMR": 176, "_id": 22905, "name": "Grumpy Old Men", "prestige": 3918, "prestige_lvl": 750}, "22935": {"MMR": 300, "_id": 22935, "name": "BlackThunder", "prestige": 5925, "prestige_lvl": 525}, "22936": {"MMR": 188, "_id": 22936, "name": "badass", "prestige": 3609, "prestige_lvl": 225}, "22989": {"MMR": 300, "_id": 22989, "name": "So so", "prestige": 5900, "prestige_lvl": 500}, "23011": {"MMR": 138, "_id": 23011, "name": "L'Illuminati", "prestige": 2859, "prestige_lvl": 375}, "23019": {"MMR": 222, "_id": 23019, "name": "balmy beach", "prestige": 4603, "prestige_lvl": 575}, "23074": {"MMR": 0, "_id": 23074, "name": "moja ku\u0107a", "prestige": 375, "prestige_lvl": 375}, "23135": {"MMR": 413, "_id": 23135, "name": "Young Nation", "prestige": 7834, "prestige_lvl": 400}, "23141": {"MMR": 263, "_id": 23141, "name": "Twisted Reality", "prestige": 4959, "prestige_lvl": 225}, "23142": {"MMR": 0, "_id": 23142, "name": "it's hardtoplay nice", "prestige": 350, "prestige_lvl": 350}, "23157": {"MMR": 100, "_id": 23157, "name": "Sentinels", "prestige": 2300, "prestige_lvl": 500}, "23165": {"MMR": 0, "_id": 23165, "name": "Everlong 2", "prestige": 425, "prestige_lvl": 425}, "23182": {"MMR": 250, "_id": 23182, "name": "Pogles Wood", "prestige": 5075, "prestige_lvl": 575}, "23187": {"MMR": 13, "_id": 23187, "name": "One hand", "prestige": 584, "prestige_lvl": 350}, "23191": {"MMR": 225, "_id": 23191, "name": "Da Man Sep", "prestige": 4400, "prestige_lvl": 350}, "23200": {"MMR": 475, "_id": 23200, "name": "Clearwater", "prestige": 9150, "prestige_lvl": 600}, "23210": {"MMR": 125, "_id": 23210, "name": "Samsara Diamonds", "prestige": 2775, "prestige_lvl": 525}, "23289": {"MMR": 200, "_id": 23289, "name": "Just us", "prestige": 4050, "prestige_lvl": 450}, "23292": {"MMR": 50, "_id": 23292, "name": "Ravens Horde", "prestige": 1350, "prestige_lvl": 450}, "23295": {"MMR": 300, "_id": 23295, "name": "Lost Universe", "prestige": 5775, "prestige_lvl": 375}, "23343": {"MMR": 281, "_id": 23343, "name": "Zero Point Gravity", "prestige": 5633, "prestige_lvl": 575}, "23359": {"MMR": 200, "_id": 23359, "name": "Neosapien Order", "prestige": 4100, "prestige_lvl": 500}, "23375": {"MMR": 0, "_id": 23375, "name": "Outlander", "prestige": 350, "prestige_lvl": 350}, "23383": {"MMR": 113, "_id": 23383, "name": "Expeditionnary Corp.", "prestige": 2484, "prestige_lvl": 450}, "23399": {"MMR": 125, "_id": 23399, "name": "The Cobras", "prestige": 2825, "prestige_lvl": 575}, "23419": {"MMR": 0, "_id": 23419, "name": "The High Council", "prestige": 425, "prestige_lvl": 425}, "23427": {"MMR": 150, "_id": 23427, "name": "The Mandalorian", "prestige": 3200, "prestige_lvl": 500}, "23458": {"MMR": 0, "_id": 23458, "name": "The Marines", "prestige": 450, "prestige_lvl": 450}, "23536": {"MMR": 25, "_id": 23536, "name": "Dracones Flamma", "prestige": 900, "prestige_lvl": 450}, "23550": {"MMR": 175, "_id": 23550, "name": "Bereans", "prestige": 3650, "prestige_lvl": 500}, "23554": {"MMR": 50, "_id": 23554, "name": "The One and only", "prestige": 1400, "prestige_lvl": 500}, "23582": {"MMR": 275, "_id": 23582, "name": "Fellowship", "prestige": 5525, "prestige_lvl": 575}, "23594": {"MMR": 125, "_id": 23594, "name": "Family Guys", "prestige": 2775, "prestige_lvl": 525}, "23596": {"MMR": 0, "_id": 23596, "name": "Si Thut", "prestige": 450, "prestige_lvl": 450}, "23609": {"MMR": 425, "_id": 23609, "name": "Alliance", "prestige": 8225, "prestige_lvl": 575}, "23633": {"MMR": 718, "_id": 23633, "name": "Fellowship of Celts", "prestige": 13749, "prestige_lvl": 825}, "23679": {"MMR": 175, "_id": 23679, "name": "Sniper Den", "prestige": 3650, "prestige_lvl": 500}, "23692": {"MMR": 225, "_id": 23692, "name": "justmetv", "prestige": 4575, "prestige_lvl": 525}, "23721": {"MMR": 225, "_id": 23721, "name": "Chillin it", "prestige": 4575, "prestige_lvl": 525}, "23775": {"MMR": 5, "_id": 23775, "name": "The crows nest", "prestige": 465, "prestige_lvl": 375}, "23784": {"MMR": 0, "_id": 23784, "name": "Lux1", "prestige": 350, "prestige_lvl": 350}, "23796": {"MMR": 500, "_id": 23796, "name": "TST", "prestige": 9575, "prestige_lvl": 575}, "23805": {"MMR": 188, "_id": 23805, "name": "Gathered Ancients", "prestige": 3659, "prestige_lvl": 275}, "23823": {"MMR": 263, "_id": 23823, "name": "The Toon Army", "prestige": 5338, "prestige_lvl": 600}, "23826": {"MMR": 350, "_id": 23826, "name": "INDIAN CIVILISATION", "prestige": 6875, "prestige_lvl": 575}, "23827": {"MMR": 0, "_id": 23827, "name": "Alliance of Arvahall", "prestige": 400, "prestige_lvl": 400}, "23863": {"MMR": 0, "_id": 23863, "name": "Freenation", "prestige": 400, "prestige_lvl": 400}, "23864": {"MMR": 375, "_id": 23864, "name": "Argyle-DM", "prestige": 7275, "prestige_lvl": 525}, "23872": {"MMR": 383, "_id": 23872, "name": "Jungle Warriors", "prestige": 7965, "prestige_lvl": 575}, "23881": {"MMR": 288, "_id": 23881, "name": "N' One", "prestige": 5634, "prestige_lvl": 450}, "23894": {"MMR": 363, "_id": 23894, "name": "Adeelia Empire", "prestige": 6959, "prestige_lvl": 425}, "23895": {"MMR": 0, "_id": 23895, "name": "Pirates", "prestige": 400, "prestige_lvl": 400}, "23939": {"MMR": 263, "_id": 23939, "name": "Satellites", "prestige": 5184, "prestige_lvl": 450}, "23992": {"MMR": 475, "_id": 23992, "name": "El Lone Lobo", "prestige": 9125, "prestige_lvl": 575}, "24006": {"MMR": 188, "_id": 24006, "name": "Hannibal Knights", "prestige": 3609, "prestige_lvl": 225}, "24014": {"MMR": 375, "_id": 24014, "name": "Victorious1", "prestige": 7300, "prestige_lvl": 550}, "24024": {"MMR": 425, "_id": 24024, "name": "Onopordum", "prestige": 8225, "prestige_lvl": 575}, "24048": {"MMR": 300, "_id": 24048, "name": "welsh tribe", "prestige": 5950, "prestige_lvl": 550}, "24053": {"MMR": 235, "_id": 24053, "name": "Moon Queens", "prestige": 4705, "prestige_lvl": 475}, "24082": {"MMR": 400, "_id": 24082, "name": "Les Enfants Terrible", "prestige": 7625, "prestige_lvl": 425}, "24112": {"MMR": 183, "_id": 24112, "name": "Jugoslavija rules", "prestige": 3794, "prestige_lvl": 500}, "24113": {"MMR": 250, "_id": 24113, "name": "The Blue Ocean", "prestige": 5025, "prestige_lvl": 525}, "24117": {"MMR": 238, "_id": 24117, "name": "Serenity valley", "prestige": 4609, "prestige_lvl": 325}, "24150": {"MMR": 263, "_id": 24150, "name": "TooHIGH", "prestige": 4959, "prestige_lvl": 225}, "24153": {"MMR": 525, "_id": 24153, "name": "\ud83e\uddd8\ud83c\udffb\u200d\u2640\ufe0f\ud83e\uddd8\ud83c\udffb\u200d\u2640\ufe0f", "prestige": 10843, "prestige_lvl": 625}, "24160": {"MMR": 25, "_id": 24160, "name": "Nah", "prestige": 900, "prestige_lvl": 450}, "24170": {"MMR": 75, "_id": 24170, "name": "Joel's Squad", "prestige": 1875, "prestige_lvl": 525}, "24187": {"MMR": 388, "_id": 24187, "name": "Rousse", "prestige": 7509, "prestige_lvl": 525}, "24189": {"MMR": 75, "_id": 24189, "name": "Dliug", "prestige": 1875, "prestige_lvl": 525}, "24216": {"MMR": 68, "_id": 24216, "name": "Lagertha Warriors", "prestige": 1449, "prestige_lvl": 225}, "24221": {"MMR": 30, "_id": 24221, "name": "Yolo", "prestige": 990, "prestige_lvl": 450}, "24233": {"MMR": 275, "_id": 24233, "name": "APALINA", "prestige": 5525, "prestige_lvl": 575}, "24234": {"MMR": 263, "_id": 24234, "name": "Snakebite", "prestige": 5034, "prestige_lvl": 300}, "24238": {"MMR": 250, "_id": 24238, "name": "NOPE", "prestige": 5000, "prestige_lvl": 500}, "24248": {"MMR": 0, "_id": 24248, "name": "FreeStyle", "prestige": 425, "prestige_lvl": 425}, "24250": {"MMR": 338, "_id": 24250, "name": "Apes of the North", "prestige": 6534, "prestige_lvl": 450}, "24259": {"MMR": 680, "_id": 24259, "name": "Smooth Operators", "prestige": 15021, "prestige_lvl": 800}, "24260": {"MMR": 313, "_id": 24260, "name": "THUNDER 2.0", "prestige": 6009, "prestige_lvl": 375}, "24272": {"MMR": 88, "_id": 24272, "name": "Valhalla", "prestige": 1909, "prestige_lvl": 325}, "24277": {"MMR": 25, "_id": 24277, "name": "deixames\u00f3", "prestige": 800, "prestige_lvl": 350}, "24288": {"MMR": 313, "_id": 24288, "name": "-Storm-", "prestige": 6084, "prestige_lvl": 450}, "24325": {"MMR": 113, "_id": 24325, "name": "Albion Knights", "prestige": 2259, "prestige_lvl": 225}, "24328": {"MMR": 450, "_id": 24328, "name": "Kun Diaow", "prestige": 8810, "prestige_lvl": 550}, "24332": {"MMR": 263, "_id": 24332, "name": "Fun4All", "prestige": 5134, "prestige_lvl": 400}, "24338": {"MMR": 38, "_id": 24338, "name": "Madammims", "prestige": 959, "prestige_lvl": 275}, "24350": {"MMR": 225, "_id": 24350, "name": "Sleeping!  Shhh!", "prestige": 4550, "prestige_lvl": 500}, "24354": {"MMR": 250, "_id": 24354, "name": "FOE & Chill", "prestige": 4975, "prestige_lvl": 475}, "24365": {"MMR": 250, "_id": 24365, "name": "CaucasusStar \ud83c\udde6\ud83c\uddff", "prestige": 4975, "prestige_lvl": 475}, "24366": {"MMR": 225, "_id": 24366, "name": "The White Witches", "prestige": 4300, "prestige_lvl": 250}, "24370": {"MMR": 263, "_id": 24370, "name": "Belekas", "prestige": 5084, "prestige_lvl": 350}, "24377": {"MMR": 263, "_id": 24377, "name": "\u016bnus", "prestige": 5109, "prestige_lvl": 375}, "24400": {"MMR": 375, "_id": 24400, "name": "The Monster Squad", "prestige": 7275, "prestige_lvl": 525}, "24410": {"MMR": 350, "_id": 24410, "name": "Proud Kiwi", "prestige": 6775, "prestige_lvl": 475}, "24412": {"MMR": 313, "_id": 24412, "name": "Pixies Place", "prestige": 6034, "prestige_lvl": 400}, "24468": {"MMR": 388, "_id": 24468, "name": "Alphas", "prestige": 7384, "prestige_lvl": 400}, "24476": {"MMR": 475, "_id": 24476, "name": "The vRS Guild", "prestige": 9000, "prestige_lvl": 450}, "24478": {"MMR": 375, "_id": 24478, "name": "Mad Merkin Farmers", "prestige": 7250, "prestige_lvl": 500}, "24500": {"MMR": 263, "_id": 24500, "name": "afk", "prestige": 4959, "prestige_lvl": 225}, "24502": {"MMR": 78, "_id": 24502, "name": "Freya", "prestige": 1629, "prestige_lvl": 225}, "24531": {"MMR": 38, "_id": 24531, "name": "The Golden Toad", "prestige": 884, "prestige_lvl": 200}, "24537": {"MMR": 263, "_id": 24537, "name": "Fair For All", "prestige": 4959, "prestige_lvl": 225}, "24540": {"MMR": 88, "_id": 24540, "name": "Diamante", "prestige": 1884, "prestige_lvl": 300}, "24542": {"MMR": 188, "_id": 24542, "name": "collection", "prestige": 3609, "prestige_lvl": 225}, "24550": {"MMR": 213, "_id": 24550, "name": "dim", "prestige": 4159, "prestige_lvl": 325}, "24556": {"MMR": 350, "_id": 24556, "name": "Issues", "prestige": 6725, "prestige_lvl": 425}, "24557": {"MMR": 53, "_id": 24557, "name": "The First Order", "prestige": 1279, "prestige_lvl": 325}, "24561": {"MMR": 263, "_id": 24561, "name": "Ed's guild", "prestige": 5134, "prestige_lvl": 400}, "24590": {"MMR": 225, "_id": 24590, "name": "Build And Trade", "prestige": 4550, "prestige_lvl": 500}, "24595": {"MMR": 0, "_id": 24595, "name": "SnowDog", "prestige": 384, "prestige_lvl": 300}, "24596": {"MMR": 375, "_id": 24596, "name": "Spuddlers", "prestige": 7125, "prestige_lvl": 375}, "24602": {"MMR": 125, "_id": 24602, "name": "Coming for you", "prestige": 2650, "prestige_lvl": 400}, "24614": {"MMR": 300, "_id": 24614, "name": "Avallion", "prestige": 5825, "prestige_lvl": 425}, "24622": {"MMR": 513, "_id": 24622, "name": "Trogs", "prestige": 9684, "prestige_lvl": 450}, "24635": {"MMR": 263, "_id": 24635, "name": "Hakhamaneshyan", "prestige": 4984, "prestige_lvl": 250}, "24658": {"MMR": 363, "_id": 24658, "name": "Dark Matter", "prestige": 6884, "prestige_lvl": 350}, "24680": {"MMR": 213, "_id": 24680, "name": "sofaking great guild", "prestige": 4184, "prestige_lvl": 350}, "24687": {"MMR": 40, "_id": 24687, "name": "we are free", "prestige": 945, "prestige_lvl": 225}, "24724": {"MMR": 225, "_id": 24724, "name": "Bobby's Kingdom", "prestige": 4275, "prestige_lvl": 225}, "24726": {"MMR": 400, "_id": 24726, "name": "The NetherGuard", "prestige": 7650, "prestige_lvl": 450}, "24741": {"MMR": 225, "_id": 24741, "name": "RagingCareBears\ud83d\udc3b", "prestige": 4275, "prestige_lvl": 225}, "24768": {"MMR": 263, "_id": 24768, "name": "event friends", "prestige": 5009, "prestige_lvl": 275}, "24770": {"MMR": 188, "_id": 24770, "name": "Guild 5070", "prestige": 3609, "prestige_lvl": 225}, "24786": {"MMR": 263, "_id": 24786, "name": "Bobalone", "prestige": 4959, "prestige_lvl": 225}, "24798": {"MMR": 188, "_id": 24798, "name": "Naya Samsara", "prestige": 4048, "prestige_lvl": 600}, "24801": {"MMR": 263, "_id": 24801, "name": "Dinegu Dims Hunters", "prestige": 4959, "prestige_lvl": 225}, "24806": {"MMR": 225, "_id": 24806, "name": "Redeemed Ones", "prestige": 4300, "prestige_lvl": 250}, "24809": {"MMR": 188, "_id": 24809, "name": "Hilltop", "prestige": 3609, "prestige_lvl": 225}, "24850": {"MMR": 0, "_id": 24850, "name": "RDR2", "prestige": 528, "prestige_lvl": 200}, "24905": {"MMR": 0, "_id": 24905, "name": "Rektum Explorer", "prestige": 1151, "prestige_lvl": 175}, "24926": {"MMR": 0, "_id": 24926, "name": "Meereen", "prestige": 838, "prestige_lvl": 150}, "24988": {"MMR": 0, "_id": 24988, "name": "Vampire Hunter", "prestige": 1840, "prestige_lvl": 100}}